[
    {
        "id": "Krazyer/klstorage/azure/1.0.0",
        "owner": "",
        "namespace": "Krazyer",
        "name": "klstorage",
        "version": "1.0.0",
        "provider": "azure",
        "provider_logo_url": "/images/providers/azure.png?3",
        "description": "",
        "source": "https://github.com/Krazyer/terraform-azure-klstorage",
        "tag": "v1.0.0",
        "published_at": "2022-12-28T10:26:18.475393Z",
        "downloads": 0,
        "verified": false
    },
    {
        "id": "vmwaregopi/divyastorage/azure/1.0.0",
        "owner": "",
        "namespace": "vmwaregopi",
        "name": "divyastorage",
        "version": "1.0.0",
        "provider": "azure",
        "provider_logo_url": "/images/providers/azure.png?3",
        "description": "",
        "source": "https://github.com/vmwaregopi/terraform-azure-divyastorage",
        "tag": "v1.0.0",
        "published_at": "2022-12-28T10:26:28.584039Z",
        "downloads": 0,
        "verified": false
    },
    {
        "id": "nitin42nagpal/Nitinstorage/azure/2.0.1",
        "owner": "",
        "namespace": "nitin42nagpal",
        "name": "Nitinstorage",
        "version": "2.0.1",
        "provider": "azure",
        "provider_logo_url": "/images/providers/azure.png?3",
        "description": "",
        "source": "https://github.com/nitin42nagpal/terraform-azure-Nitinstorage",
        "tag": "v2.0.1",
        "published_at": "2022-12-28T10:46:33.081639Z",
        "downloads": 0,
        "verified": false
    },
    {
        "id": "Lavanya2509/module/azure/1.0.0",
        "owner": "",
        "namespace": "Lavanya2509",
        "name": "module",
        "version": "1.0.0",
        "provider": "azure",
        "provider_logo_url": "/images/providers/azure.png?3",
        "description": "",
        "source": "https://github.com/Lavanya2509/terraform-azure-module",
        "tag": "v1.0.0",
        "published_at": "2022-12-28T10:46:48.215119Z",
        "downloads": 0,
        "verified": false
    },
    {
        "id": "surendra0802/surenstorage/azure/1.0.0",
        "owner": "",
        "namespace": "surendra0802",
        "name": "surenstorage",
        "version": "1.0.0",
        "provider": "azure",
        "provider_logo_url": "/images/providers/azure.png?3",
        "description": "",
        "source": "https://github.com/surendra0802/terraform-azure-surenstorage",
        "tag": "v1.0.0",
        "published_at": "2022-12-28T10:47:03.873958Z",
        "downloads": 0,
        "verified": false
    },
    {
        "id": "praveenakrishnasamy/vault/azure/1.0.0",
        "owner": "",
        "namespace": "praveenakrishnasamy",
        "name": "vault",
        "version": "1.0.0",
        "provider": "azure",
        "provider_logo_url": "/images/providers/azure.png?3",
        "description": "",
        "source": "https://github.com/praveenakrishnasamy/terraform-azure-vault",
        "tag": "v1.0.0",
        "published_at": "2022-12-28T10:47:04.269817Z",
        "downloads": 0,
        "verified": false
    },
    {
        "id": "arundeva2k18/arunstorage/azurerm/1.0.4",
        "owner": "",
        "namespace": "arundeva2k18",
        "name": "arunstorage",
        "version": "1.0.4",
        "provider": "azurerm",
        "provider_logo_url": "/images/providers/azure.png?3",
        "description": "",
        "source": "https://github.com/arundeva2k18/terraform-azurerm-arunstorage",
        "tag": "v1.0.4",
        "published_at": "2022-12-28T10:59:04.967712Z",
        "downloads": 0,
        "verified": false
    },
    {
        "id": "thara12/thara/azure/1.0.0",
        "owner": "",
        "namespace": "thara12",
        "name": "thara",
        "version": "1.0.0",
        "provider": "azure",
        "provider_logo_url": "/images/providers/azure.png?3",
        "description": "",
        "source": "https://github.com/thara12/terraform-azure-thara",
        "tag": "v1.0.0",
        "published_at": "2022-12-28T11:07:51.095185Z",
        "downloads": 0,
        "verified": false
    },
    {
        "id": "ajay21ks/storage/azure/1.0.0",
        "owner": "",
        "namespace": "ajay21ks",
        "name": "storage",
        "version": "1.0.0",
        "provider": "azure",
        "provider_logo_url": "/images/providers/azure.png?3",
        "description": "",
        "source": "https://github.com/ajay21ks/terraform-azure-storage",
        "tag": "v1.0.0",
        "published_at": "2022-12-28T11:09:29.480742Z",
        "downloads": 0,
        "verified": false
    },
    {
        "id": "Siva20221228/mystorage/azure/1.0.0",
        "owner": "",
        "namespace": "Siva20221228",
        "name": "mystorage",
        "version": "1.0.0",
        "provider": "azure",
        "provider_logo_url": "/images/providers/azure.png?3",
        "description": "",
        "source": "https://github.com/Siva20221228/terraform-azure-mystorage",
        "tag": "v1.0.0",
        "published_at": "2022-12-28T11:25:43.448118Z",
        "downloads": 0,
        "verified": false
    },
    {
        "id": "pnkjmahto029/staticwebsitepublic/azurerm/1.0.0",
        "owner": "",
        "namespace": "pnkjmahto029",
        "name": "staticwebsitepublic",
        "version": "1.0.0",
        "provider": "azurerm",
        "provider_logo_url": "/images/providers/azure.png?3",
        "description": "Terraform Modules to be shared in Terraform Public Registry",
        "source": "https://github.com/pnkjmahto029/terraform-azurerm-staticwebsitepublic",
        "tag": "1.0.0",
        "published_at": "2022-12-28T12:27:59.20515Z",
        "downloads": 1693,
        "verified": false
    },
    {
        "id": "clouddrove/vnet/azure/1.0.4",
        "owner": "",
        "namespace": "clouddrove",
        "name": "vnet",
        "version": "1.0.4",
        "provider": "azure",
        "provider_logo_url": "/images/providers/azure.png?3",
        "description": "Terraform module to create VIRTUAL-NETWORK resource on AZURE. ",
        "source": "https://github.com/clouddrove/terraform-azure-vnet",
        "tag": "1.0.4",
        "published_at": "2024-01-03T12:06:58.063819Z",
        "downloads": 6140,
        "verified": false
    },
    {
        "id": "Infrastrukturait/cloudwatch-logs/aws/0.1.0",
        "owner": "",
        "namespace": "Infrastrukturait",
        "name": "cloudwatch-logs",
        "version": "0.1.0",
        "provider": "aws",
        "provider_logo_url": "/images/providers/aws.png",
        "description": "Terraform module to provision a CloudWatch logs",
        "source": "https://github.com/Infrastrukturait/terraform-aws-cloudwatch-logs",
        "tag": "v0.1.0",
        "published_at": "2022-12-28T17:51:29.135836Z",
        "downloads": 2854,
        "verified": false
    },
    {
        "id": "Selleo/ecs/aws/0.21.0",
        "owner": "",
        "namespace": "Selleo",
        "name": "ecs",
        "version": "0.21.0",
        "provider": "aws",
        "provider_logo_url": "/images/providers/aws.png",
        "description": "Terraform ECS module",
        "source": "https://github.com/Selleo/terraform-aws-ecs",
        "tag": "v0.21.0",
        "published_at": "2024-04-23T12:39:05.412862Z",
        "downloads": 2105,
        "verified": false
    },
    {
        "id": "xumes/eks/aws/1.0.0",
        "owner": "",
        "namespace": "xumes",
        "name": "eks",
        "version": "1.0.0",
        "provider": "aws",
        "provider_logo_url": "/images/providers/aws.png",
        "description": "Creating an EKS cluster on AWS using Terraform",
        "source": "https://github.com/xumes/terraform-aws-eks",
        "tag": "1.0.0",
        "published_at": "2022-12-28T20:57:31.839074Z",
        "downloads": 0,
        "verified": false
    },
    {
        "id": "Infrastrukturait/secret-manager/aws/0.2.0",
        "owner": "",
        "namespace": "Infrastrukturait",
        "name": "secret-manager",
        "version": "0.2.0",
        "provider": "aws",
        "provider_logo_url": "/images/providers/aws.png",
        "description": "Terraform module for providing read and write access to the AWS Secret Manager values",
        "source": "https://github.com/Infrastrukturait/terraform-aws-secret-manager",
        "tag": "v0.2.0",
        "published_at": "2022-12-29T20:31:07.951448Z",
        "downloads": 2228,
        "verified": false
    },
    {
        "id": "Infrastrukturait/iam-simple/aws/0.2.0",
        "owner": "",
        "namespace": "Infrastrukturait",
        "name": "iam-simple",
        "version": "0.2.0",
        "provider": "aws",
        "provider_logo_url": "/images/providers/aws.png",
        "description": "Terraform Module to Provision a Basic IAM System",
        "source": "https://github.com/Infrastrukturait/terraform-aws-iam-simple",
        "tag": "v0.2.0",
        "published_at": "2022-12-29T21:51:12.231779Z",
        "downloads": 2211,
        "verified": false
    },
    {
        "id": "SphereEx/shardingsphere/aws/0.1.2",
        "owner": "",
        "namespace": "SphereEx",
        "name": "shardingsphere",
        "version": "0.1.2",
        "provider": "aws",
        "provider_logo_url": "/images/providers/aws.png",
        "description": "",
        "source": "https://github.com/SphereEx/terraform-aws-shardingsphere",
        "tag": "v0.1.2",
        "published_at": "2023-01-11T09:51:39.343909Z",
        "downloads": 0,
        "verified": false
    },
    {
        "id": "brainsik/dns-caa/cloudflare/2.1.0",
        "owner": "",
        "namespace": "brainsik",
        "name": "dns-caa",
        "version": "2.1.0",
        "provider": "cloudflare",
        "provider_logo_url": "/images/providers/generic.svg?2",
        "description": "Create Cloudflare DNS CAA records",
        "source": "https://github.com/brainsik/terraform-cloudflare-dns-caa",
        "tag": "v2.1.0",
        "published_at": "2024-07-02T23:40:59.944662Z",
        "downloads": 37,
        "verified": false
    },
    {
        "id": "bootlabstech/ebs-volume/aws/1.0.0",
        "owner": "",
        "namespace": "bootlabstech",
        "name": "ebs-volume",
        "version": "1.0.0",
        "provider": "aws",
        "provider_logo_url": "/images/providers/aws.png",
        "description": "",
        "source": "https://github.com/bootlabstech/terraform-aws-ebs-volume",
        "tag": "v1.0.0",
        "published_at": "2022-12-29T11:16:13.913778Z",
        "downloads": 1454,
        "verified": false
    },
    {
        "id": "bootlabstech/ecr/aws/1.0.0",
        "owner": "",
        "namespace": "bootlabstech",
        "name": "ecr",
        "version": "1.0.0",
        "provider": "aws",
        "provider_logo_url": "/images/providers/aws.png",
        "description": "",
        "source": "https://github.com/bootlabstech/terraform-aws-ecr",
        "tag": "v1.0.0",
        "published_at": "2022-12-29T11:16:39.552092Z",
        "downloads": 1556,
        "verified": false
    },
    {
        "id": "clouddrove/subnet/azure/1.2.1",
        "owner": "",
        "namespace": "clouddrove",
        "name": "subnet",
        "version": "1.2.1",
        "provider": "azure",
        "provider_logo_url": "/images/providers/azure.png?3",
        "description": "This terraform module is designed to create Azure Subnet resources.  Virtual networks and virtual machines in Azure. Microsoft Learn A subnet is a range of IP addresses in the virtual network. You can divide a virtual network into multiple subnets for organization and security. Each NIC in a VM is connected to one subnet in one virtual network.",
        "source": "https://github.com/clouddrove/terraform-azure-subnet",
        "tag": "1.2.1",
        "published_at": "2024-07-26T16:36:45.346746Z",
        "downloads": 5495,
        "verified": false
    },
    {
        "id": "bootlabstech/aurora/aws/1.0.0",
        "owner": "",
        "namespace": "bootlabstech",
        "name": "aurora",
        "version": "1.0.0",
        "provider": "aws",
        "provider_logo_url": "/images/providers/aws.png",
        "description": "Creates multiple Aurora cluster and DB",
        "source": "https://github.com/bootlabstech/terraform-aws-aurora",
        "tag": "v1.0.0",
        "published_at": "2022-12-29T12:46:58.783774Z",
        "downloads": 0,
        "verified": false
    },
    {
        "id": "RCFromCLE/jmusicbot/azure/2.0.2",
        "owner": "",
        "namespace": "RCFromCLE",
        "name": "jmusicbot",
        "version": "2.0.2",
        "provider": "azure",
        "provider_logo_url": "/images/providers/azure.png?3",
        "description": "Terraform module used as part of an automated and cost effective solution featuring TF Cloud, GH Actions, and Azure to deploy JMusicBot.\ud83c\udfb6 https://github.com/RCFromCLE/terraform-azurerm-jmusicbot-config",
        "source": "https://github.com/RCFromCLE/terraform-azure-jmusicbot",
        "tag": "v2.0.2",
        "published_at": "2024-07-22T02:41:24.583716Z",
        "downloads": 210,
        "verified": false
    },
    {
        "id": "abdullahkayretli/docker-instance/aws/0.0.1",
        "owner": "",
        "namespace": "abdullahkayretli",
        "name": "docker-instance",
        "version": "0.0.1",
        "provider": "aws",
        "provider_logo_url": "/images/providers/aws.png",
        "description": "terraform-aws-docker-instance",
        "source": "https://github.com/abdullahkayretli/terraform-aws-docker-instance",
        "tag": "v0.0.1",
        "published_at": "2022-12-29T16:19:18.012279Z",
        "downloads": 1525,
        "verified": false
    },
    {
        "id": "sculley/traefik-eks/aws/1.0.1",
        "owner": "",
        "namespace": "sculley",
        "name": "traefik-eks",
        "version": "1.0.1",
        "provider": "aws",
        "provider_logo_url": "/images/providers/aws.png",
        "description": "Terraform module to deploy Traefik into an AWS EKS Kubernetes cluster along with an ALB & ACM",
        "source": "https://github.com/sculley/terraform-aws-traefik-eks",
        "tag": "v1.0.1",
        "published_at": "2022-12-29T17:11:15.271694Z",
        "downloads": 0,
        "verified": false
    },
    {
        "id": "bootlabstech/kms-key/aws/1.0.0",
        "owner": "",
        "namespace": "bootlabstech",
        "name": "kms-key",
        "version": "1.0.0",
        "provider": "aws",
        "provider_logo_url": "/images/providers/aws.png",
        "description": "",
        "source": "https://github.com/bootlabstech/terraform-aws-kms-key",
        "tag": "v1.0.0",
        "published_at": "2022-12-29T17:50:17.685646Z",
        "downloads": 1366,
        "verified": false
    },
    {
        "id": "plus3it/tardigrade-route53-resolver/aws/3.0.0",
        "owner": "",
        "namespace": "plus3it",
        "name": "tardigrade-route53-resolver",
        "version": "3.0.0",
        "provider": "aws",
        "provider_logo_url": "/images/providers/aws.png",
        "description": "Terraform module to associate route53 resolver rules",
        "source": "https://github.com/plus3it/terraform-aws-tardigrade-route53-resolver",
        "tag": "3.0.0",
        "published_at": "2022-12-29T18:01:04.588138Z",
        "downloads": 0,
        "verified": false
    },
    {
        "id": "cloudprodigy/vpc/aws/2.0.4",
        "owner": "",
        "namespace": "cloudprodigy",
        "name": "vpc",
        "version": "2.0.4",
        "provider": "aws",
        "provider_logo_url": "/images/providers/aws.png",
        "description": "Build VPC and related components on AWS using Terraform",
        "source": "https://github.com/cloudprodigy/terraform-aws-vpc",
        "tag": "v2.0.4",
        "published_at": "2022-12-29T18:28:53.132681Z",
        "downloads": 1489,
        "verified": false
    },
    {
        "id": "bmfernand/vpc-test/aws/1.0.2",
        "owner": "",
        "namespace": "bmfernand",
        "name": "vpc-test",
        "version": "1.0.2",
        "provider": "aws",
        "provider_logo_url": "/images/providers/aws.png",
        "description": "",
        "source": "https://github.com/bmfernand/terraform-aws-vpc-test",
        "tag": "v1.0.2",
        "published_at": "2022-12-29T18:42:48.554485Z",
        "downloads": 1582,
        "verified": false
    },
    {
        "id": "sculley/vault-eks/aws/1.0.0",
        "owner": "",
        "namespace": "sculley",
        "name": "vault-eks",
        "version": "1.0.0",
        "provider": "aws",
        "provider_logo_url": "/images/providers/aws.png",
        "description": "Terraform module to deploy Vault into an AWS EKS Kubernetes cluster along with DynamoDB for storage and KMS for auto-unsealing",
        "source": "https://github.com/sculley/terraform-aws-vault-eks",
        "tag": "v1.0.0",
        "published_at": "2022-12-29T23:05:38.643671Z",
        "downloads": 0,
        "verified": false
    },
    {
        "id": "outsideopen/route53-backup-restore/aws/0.2.0",
        "owner": "",
        "namespace": "outsideopen",
        "name": "route53-backup-restore",
        "version": "0.2.0",
        "provider": "aws",
        "provider_logo_url": "/images/providers/aws.png",
        "description": "Terraform module for provisioning Route53 backup/restore lambda functions.",
        "source": "https://github.com/outsideopen/terraform-aws-route53-backup-restore",
        "tag": "0.2.0",
        "published_at": "2022-12-30T20:06:54.266509Z",
        "downloads": 1467,
        "verified": false
    },
    {
        "id": "bootlabstech/ebs-volume-snapshot/aws/1.0.0",
        "owner": "",
        "namespace": "bootlabstech",
        "name": "ebs-volume-snapshot",
        "version": "1.0.0",
        "provider": "aws",
        "provider_logo_url": "/images/providers/aws.png",
        "description": "",
        "source": "https://github.com/bootlabstech/terraform-aws-ebs-volume-snapshot",
        "tag": "v1.0.0",
        "published_at": "2022-12-30T04:17:16.867646Z",
        "downloads": 0,
        "verified": false
    },
    {
        "id": "bootlabstech/s3-new/aws/1.0.4",
        "owner": "",
        "namespace": "bootlabstech",
        "name": "s3-new",
        "version": "1.0.4",
        "provider": "aws",
        "provider_logo_url": "/images/providers/aws.png",
        "description": "",
        "source": "https://github.com/bootlabstech/terraform-aws-s3-new",
        "tag": "v1.0.4",
        "published_at": "2023-01-24T17:02:49.652289Z",
        "downloads": 1762,
        "verified": false
    },
    {
        "id": "bootlabstech/api-gateway/azurerm/1.0.7",
        "owner": "",
        "namespace": "bootlabstech",
        "name": "api-gateway",
        "version": "1.0.7",
        "provider": "azurerm",
        "provider_logo_url": "/images/providers/azure.png?3",
        "description": "Creates Azure API gateway",
        "source": "https://github.com/bootlabstech/terraform-azurerm-api-gateway",
        "tag": "v1.0.7",
        "published_at": "2023-12-15T12:35:51.8496Z",
        "downloads": 1766,
        "verified": false
    },
    {
        "id": "bootlabstech/privates3/aws/1.0.0",
        "owner": "",
        "namespace": "bootlabstech",
        "name": "privates3",
        "version": "1.0.0",
        "provider": "aws",
        "provider_logo_url": "/images/providers/aws.png",
        "description": "",
        "source": "https://github.com/bootlabstech/terraform-aws-privates3",
        "tag": "v1.0.0",
        "published_at": "2022-12-30T12:20:26.229717Z",
        "downloads": 1969,
        "verified": false
    },
    {
        "id": "RamizMrt/docker-instance-tekrar/aws/0.0.1",
        "owner": "",
        "namespace": "RamizMrt",
        "name": "docker-instance-tekrar",
        "version": "0.0.1",
        "provider": "aws",
        "provider_logo_url": "/images/providers/aws.png",
        "description": "",
        "source": "https://github.com/RamizMrt/terraform-aws-docker-instance-tekrar",
        "tag": "v0.0.1",
        "published_at": "2022-12-30T12:40:00.517434Z",
        "downloads": 0,
        "verified": false
    },
    {
        "id": "JonathanPorta/s3-static-site/aws/1.1.2",
        "owner": "",
        "namespace": "JonathanPorta",
        "name": "s3-static-site",
        "version": "1.1.2",
        "provider": "aws",
        "provider_logo_url": "/images/providers/aws.png",
        "description": "Very simple Terraform module for deploying a static site onto S3",
        "source": "https://github.com/JonathanPorta/terraform-aws-s3-static-site",
        "tag": "1.1.2",
        "published_at": "2024-05-29T01:28:37.208689Z",
        "downloads": 1793,
        "verified": false
    },
    {
        "id": "sudo-terraform-aws-modules/vpc-peering/aws/1.0.2",
        "owner": "",
        "namespace": "sudo-terraform-aws-modules",
        "name": "vpc-peering",
        "version": "1.0.2",
        "provider": "aws",
        "provider_logo_url": "/images/providers/aws.png",
        "description": "Terraform module to implement VPC Peering",
        "source": "https://github.com/sudo-terraform-aws-modules/terraform-aws-vpc-peering",
        "tag": "v1.0.2",
        "published_at": "2022-12-31T17:18:51.008919Z",
        "downloads": 1535,
        "verified": false
    },
    {
        "id": "Selleo/rds/aws/0.7.0",
        "owner": "",
        "namespace": "Selleo",
        "name": "rds",
        "version": "0.7.0",
        "provider": "aws",
        "provider_logo_url": "/images/providers/aws.png",
        "description": "Collection of terraform modules for RDS",
        "source": "https://github.com/Selleo/terraform-aws-rds",
        "tag": "v0.7.0",
        "published_at": "2024-01-29T10:29:06.114655Z",
        "downloads": 1720,
        "verified": false
    },
    {
        "id": "kutlay21/docker-instance/aws/0.0.1",
        "owner": "",
        "namespace": "kutlay21",
        "name": "docker-instance",
        "version": "0.0.1",
        "provider": "aws",
        "provider_logo_url": "/images/providers/aws.png",
        "description": "",
        "source": "https://github.com/kutlay21/terraform-aws-docker-instance",
        "tag": "v0.0.1",
        "published_at": "2022-12-31T17:54:37.448307Z",
        "downloads": 1518,
        "verified": false
    },
    {
        "id": "gopal1409/staticwebsite/azurerm/1.0.0",
        "owner": "",
        "namespace": "gopal1409",
        "name": "staticwebsite",
        "version": "1.0.0",
        "provider": "azurerm",
        "provider_logo_url": "/images/providers/azure.png?3",
        "description": "terraform static website module",
        "source": "https://github.com/gopal1409/terraform-azurerm-staticwebsite",
        "tag": "1.0.0",
        "published_at": "2023-01-02T02:40:09.959105Z",
        "downloads": 1505,
        "verified": false
    },
    {
        "id": "uceumice/simple-login/cloudflare/0.0.3",
        "owner": "",
        "namespace": "uceumice",
        "name": "simple-login",
        "version": "0.0.3",
        "provider": "cloudflare",
        "provider_logo_url": "/images/providers/generic.svg?2",
        "description": "",
        "source": "https://github.com/uceumice/terraform-cloudflare-simple-login",
        "tag": "0.0.3",
        "published_at": "2023-07-07T12:12:24.339612Z",
        "downloads": 36,
        "verified": false
    },
    {
        "id": "clouddrove/service-bus/azure/1.0.0",
        "owner": "",
        "namespace": "clouddrove",
        "name": "service-bus",
        "version": "1.0.0",
        "provider": "azure",
        "provider_logo_url": "/images/providers/azure.png?3",
        "description": "",
        "source": "https://github.com/clouddrove/terraform-azure-service-bus",
        "tag": "1.0.0",
        "published_at": "2023-01-02T08:40:46.439701Z",
        "downloads": 1758,
        "verified": false
    },
    {
        "id": "netascode/vspan-session/aci/0.3.0",
        "owner": "",
        "namespace": "netascode",
        "name": "vspan-session",
        "version": "0.3.0",
        "provider": "aci",
        "provider_logo_url": "/images/providers/generic.svg?2",
        "description": "Terraform Cisco ACI VSPAN Session Module",
        "source": "https://github.com/netascode/terraform-aci-vspan-session",
        "tag": "v0.3.0",
        "published_at": "2024-01-12T13:49:38.395108Z",
        "downloads": 9874,
        "verified": false
    },
    {
        "id": "vnisolutions/vpc/aws/1.2.0",
        "owner": "",
        "namespace": "vnisolutions",
        "name": "vpc",
        "version": "1.2.0",
        "provider": "aws",
        "provider_logo_url": "/images/providers/aws.png",
        "description": "",
        "source": "https://github.com/vnisolutions/terraform-aws-vpc",
        "tag": "v1.2.0",
        "published_at": "2023-01-11T02:56:39.471785Z",
        "downloads": 1533,
        "verified": false
    },
    {
        "id": "vnisolutions/s3/aws/1.1.0",
        "owner": "",
        "namespace": "vnisolutions",
        "name": "s3",
        "version": "1.1.0",
        "provider": "aws",
        "provider_logo_url": "/images/providers/aws.png",
        "description": "",
        "source": "https://github.com/vnisolutions/terraform-aws-s3",
        "tag": "v1.1.0",
        "published_at": "2023-01-02T16:00:36.742378Z",
        "downloads": 1550,
        "verified": false
    },
    {
        "id": "vnisolutions/bastion/aws/1.1.1",
        "owner": "",
        "namespace": "vnisolutions",
        "name": "bastion",
        "version": "1.1.1",
        "provider": "aws",
        "provider_logo_url": "/images/providers/aws.png",
        "description": "",
        "source": "https://github.com/vnisolutions/terraform-aws-bastion",
        "tag": "v1.1.1",
        "published_at": "2023-11-21T02:01:51.388294Z",
        "downloads": 1538,
        "verified": false
    },
    {
        "id": "web-virtua-aws-multi-account-modules/load-balancer/aws/1.0.2",
        "owner": "",
        "namespace": "web-virtua-aws-multi-account-modules",
        "name": "load-balancer",
        "version": "1.0.2",
        "provider": "aws",
        "provider_logo_url": "/images/providers/aws.png",
        "description": "",
        "source": "https://github.com/web-virtua-aws-multi-account-modules/terraform-aws-load-balancer",
        "tag": "v1.0.2",
        "published_at": "2023-01-05T19:04:40.39164Z",
        "downloads": 1533,
        "verified": false
    },
    {
        "id": "web-virtua-aws-multi-account-modules/acm/aws/1.0.5",
        "owner": "",
        "namespace": "web-virtua-aws-multi-account-modules",
        "name": "acm",
        "version": "1.0.5",
        "provider": "aws",
        "provider_logo_url": "/images/providers/aws.png",
        "description": "",
        "source": "https://github.com/web-virtua-aws-multi-account-modules/terraform-aws-acm",
        "tag": "v1.0.5",
        "published_at": "2023-02-16T20:25:54.341654Z",
        "downloads": 1542,
        "verified": false
    },
    {
        "id": "OmnipotentOwl/enterprise-scale-aks/azurerm/1.2.0",
        "owner": "",
        "namespace": "OmnipotentOwl",
        "name": "enterprise-scale-aks",
        "version": "1.2.0",
        "provider": "azurerm",
        "provider_logo_url": "/images/providers/azure.png?3",
        "description": "Terraform Module for deploying an AKS cluster following Microsoft's Cloud Adoption Framework",
        "source": "https://github.com/OmnipotentOwl/terraform-azurerm-enterprise-scale-aks",
        "tag": "v1.2.0",
        "published_at": "2023-04-08T00:04:33.463765Z",
        "downloads": 1490,
        "verified": false
    },
    {
        "id": "bhandary1419/docker-instance-1/aws/0.0.1",
        "owner": "",
        "namespace": "bhandary1419",
        "name": "docker-instance-1",
        "version": "0.0.1",
        "provider": "aws",
        "provider_logo_url": "/images/providers/aws.png",
        "description": "",
        "source": "https://github.com/bhandary1419/terraform-aws-docker-instance-1",
        "tag": "v0.0.1",
        "published_at": "2023-01-03T04:25:18.690601Z",
        "downloads": 1510,
        "verified": false
    },
    {
        "id": "bootlabstech/ec2/aws/1.0.6",
        "owner": "",
        "namespace": "bootlabstech",
        "name": "ec2",
        "version": "1.0.6",
        "provider": "aws",
        "provider_logo_url": "/images/providers/aws.png",
        "description": "",
        "source": "https://github.com/bootlabstech/terraform-aws-ec2",
        "tag": "v1.0.6",
        "published_at": "2023-05-24T06:35:29.453469Z",
        "downloads": 2320,
        "verified": false
    },
    {
        "id": "aliabbasjaffri/modules/aws/0.0.6",
        "owner": "",
        "namespace": "aliabbasjaffri",
        "name": "modules",
        "version": "0.0.6",
        "provider": "aws",
        "provider_logo_url": "/images/providers/aws.png",
        "description": "Opta AWS modules for terraform module registry",
        "source": "https://github.com/aliabbasjaffri/terraform-aws-modules",
        "tag": "v0.0.6",
        "published_at": "2023-01-04T10:02:48.174083Z",
        "downloads": 1530,
        "verified": false
    },
    {
        "id": "oslokommune/shared-vpc-tagger/aws/1.0.0",
        "owner": "",
        "namespace": "oslokommune",
        "name": "shared-vpc-tagger",
        "version": "1.0.0",
        "provider": "aws",
        "provider_logo_url": "/images/providers/aws.png",
        "description": "Tags VPCs and subnets that you did not create yourself (ie. shared VPCs)",
        "source": "https://github.com/oslokommune/terraform-aws-shared-vpc-tagger",
        "tag": "v1.0.0",
        "published_at": "2023-01-03T14:28:32.989054Z",
        "downloads": 1600,
        "verified": false
    },
    {
        "id": "mrnim94/elasticache-secondary-on-global-datastore/aws/1.0.1",
        "owner": "",
        "namespace": "mrnim94",
        "name": "elasticache-secondary-on-global-datastore",
        "version": "1.0.1",
        "provider": "aws",
        "provider_logo_url": "/images/providers/aws.png",
        "description": "This module helps you to create an Elasticache secondary (Redis) based on the Global Datastore that was made beforehand.",
        "source": "https://github.com/mrnim94/terraform-aws-elasticache-secondary-on-global-datastore",
        "tag": "1.0.1",
        "published_at": "2023-01-03T18:35:49.209157Z",
        "downloads": 0,
        "verified": false
    },
    {
        "id": "unionai-oss/modules/opta/0.0.5",
        "owner": "",
        "namespace": "unionai-oss",
        "name": "modules",
        "version": "0.0.5",
        "provider": "opta",
        "provider_logo_url": "/images/providers/generic.svg?2",
        "description": "The next generation of Infrastructure-as-Code. Work with high-level constructs instead of getting lost in low-level cloud configuration.",
        "source": "https://github.com/unionai-oss/terraform-opta-modules",
        "tag": "v0.0.5",
        "published_at": "2023-01-04T09:34:05.843067Z",
        "downloads": 0,
        "verified": false
    },
    {
        "id": "vnisolutions/elasticache-redis/aws/1.0.0",
        "owner": "",
        "namespace": "vnisolutions",
        "name": "elasticache-redis",
        "version": "1.0.0",
        "provider": "aws",
        "provider_logo_url": "/images/providers/aws.png",
        "description": "",
        "source": "https://github.com/vnisolutions/terraform-aws-elasticache-redis",
        "tag": "v1.0.0",
        "published_at": "2023-01-04T11:41:02.930639Z",
        "downloads": 1527,
        "verified": false
    },
    {
        "id": "getindata/schema/snowflake/1.5.0",
        "owner": "",
        "namespace": "getindata",
        "name": "schema",
        "version": "1.5.0",
        "provider": "snowflake",
        "provider_logo_url": "/images/providers/generic.svg?2",
        "description": "Terraform module for managing Snowflake schemas",
        "source": "https://github.com/getindata/terraform-snowflake-schema",
        "tag": "v1.5.0",
        "published_at": "2024-01-11T10:22:17.314921Z",
        "downloads": 6140,
        "verified": false
    },
    {
        "id": "ivandelic/cn-vcn/oci/1.0.4",
        "owner": "",
        "namespace": "ivandelic",
        "name": "cn-vcn",
        "version": "1.0.4",
        "provider": "oci",
        "provider_logo_url": "/images/providers/oracle.svg",
        "description": "OCI Cloud Native VCN is an MVP-like Virtual Cloud Network designed to support cloud-native workloads. It's tailored to support integrated communication for cloud-native components, such as Container Engine for Kubernetes (OKE), Functions, Container Instances, and others.",
        "source": "https://github.com/ivandelic/terraform-oci-cn-vcn",
        "tag": "v1.0.4",
        "published_at": "2024-05-09T13:50:39.109619Z",
        "downloads": 28,
        "verified": false
    },
    {
        "id": "rallyware/apps/argocd/0.2.3",
        "owner": "",
        "namespace": "rallyware",
        "name": "apps",
        "version": "0.2.3",
        "provider": "argocd",
        "provider_logo_url": "/images/providers/generic.svg?2",
        "description": "Terraform module to provision ArgoCD applications using app of apps pattern.",
        "source": "https://github.com/rallyware/terraform-argocd-apps",
        "tag": "v0.2.3",
        "published_at": "2024-05-08T16:16:25.715795Z",
        "downloads": 161396,
        "verified": false
    },
    {
        "id": "ptonini/get-manifests/kubectl/2.0.0",
        "owner": "",
        "namespace": "ptonini",
        "name": "get-manifests",
        "version": "2.0.0",
        "provider": "kubectl",
        "provider_logo_url": "/images/providers/generic.svg?2",
        "description": "",
        "source": "https://github.com/ptonini/terraform-kubectl-get-manifests",
        "tag": "v2.0.0",
        "published_at": "2023-01-04T20:10:31.828959Z",
        "downloads": 89,
        "verified": false
    },
    {
        "id": "web-virtua-aws-multi-account-modules/alb-acm-records/aws/1.0.1",
        "owner": "",
        "namespace": "web-virtua-aws-multi-account-modules",
        "name": "alb-acm-records",
        "version": "1.0.1",
        "provider": "aws",
        "provider_logo_url": "/images/providers/aws.png",
        "description": "",
        "source": "https://github.com/web-virtua-aws-multi-account-modules/terraform-aws-alb-acm-records",
        "tag": "v1.0.1",
        "published_at": "2023-01-05T18:35:44.584093Z",
        "downloads": 1508,
        "verified": false
    },
    {
        "id": "data-platform-hq/static-site/azurerm/1.0.1",
        "owner": "",
        "namespace": "data-platform-hq",
        "name": "static-site",
        "version": "1.0.1",
        "provider": "azurerm",
        "provider_logo_url": "/images/providers/azure.png?3",
        "description": "Terraform module for managing Azure Static Web Apps",
        "source": "https://github.com/data-platform-hq/terraform-azurerm-static-site",
        "tag": "v1.0.1",
        "published_at": "2023-01-05T19:37:09.286168Z",
        "downloads": 5168,
        "verified": false
    },
    {
        "id": "qbeyond/service-account/google/0.1.0",
        "owner": "",
        "namespace": "qbeyond",
        "name": "service-account",
        "version": "0.1.0",
        "provider": "google",
        "provider_logo_url": "/images/providers/google-cloud.svg",
        "description": "Terraform Module to create a google service account",
        "source": "https://github.com/qbeyond/terraform-google-service-account",
        "tag": "0.1.0",
        "published_at": "2023-01-05T10:03:12.139006Z",
        "downloads": 1461,
        "verified": false
    },
    {
        "id": "m4xmorris/protonmail/cloudflare/1.1.1",
        "owner": "",
        "namespace": "m4xmorris",
        "name": "protonmail",
        "version": "1.1.1",
        "provider": "cloudflare",
        "provider_logo_url": "/images/providers/generic.svg?2",
        "description": "Terraform module to configure a domain for ProtonMail",
        "source": "https://github.com/m4xmorris/terraform-cloudflare-protonmail",
        "tag": "v1.1.1",
        "published_at": "2023-01-08T12:08:53.186445Z",
        "downloads": 137,
        "verified": false
    },
    {
        "id": "m4xmorris/static-site/digitalocean/1.3.2",
        "owner": "",
        "namespace": "m4xmorris",
        "name": "static-site",
        "version": "1.3.2",
        "provider": "digitalocean",
        "provider_logo_url": "/images/providers/digitalocean.png",
        "description": "Terraform module for deploying static sites to DigitalOcean's App Platform",
        "source": "https://github.com/m4xmorris/terraform-digitalocean-static-site",
        "tag": "v1.3.2",
        "published_at": "2023-12-14T16:22:27.332652Z",
        "downloads": 733,
        "verified": false
    },
    {
        "id": "colinwilson/plausible/docker/0.1.3",
        "owner": "",
        "namespace": "colinwilson",
        "name": "plausible",
        "version": "0.1.3",
        "provider": "docker",
        "provider_logo_url": "/images/providers/generic.svg?2",
        "description": "Terraform module to deploy Plausible Analytics on Docker Swarm",
        "source": "https://github.com/colinwilson/terraform-docker-plausible",
        "tag": "0.1.3",
        "published_at": "2023-07-13T10:27:26.545585Z",
        "downloads": 0,
        "verified": false
    },
    {
        "id": "vnisolutions/ecs-fargate/aws/1.5.0",
        "owner": "",
        "namespace": "vnisolutions",
        "name": "ecs-fargate",
        "version": "1.5.0",
        "provider": "aws",
        "provider_logo_url": "/images/providers/aws.png",
        "description": "",
        "source": "https://github.com/vnisolutions/terraform-aws-ecs-fargate",
        "tag": "v1.5.0",
        "published_at": "2023-01-30T07:16:53.806014Z",
        "downloads": 1549,
        "verified": false
    },
    {
        "id": "vnisolutions/alb/aws/1.3.0",
        "owner": "",
        "namespace": "vnisolutions",
        "name": "alb",
        "version": "1.3.0",
        "provider": "aws",
        "provider_logo_url": "/images/providers/aws.png",
        "description": "",
        "source": "https://github.com/vnisolutions/terraform-aws-alb",
        "tag": "v1.3.0",
        "published_at": "2023-01-31T03:15:38.268943Z",
        "downloads": 1539,
        "verified": false
    },
    {
        "id": "tonyskidmore/vmss-devops-agent/azurerm/0.2.6",
        "owner": "",
        "namespace": "tonyskidmore",
        "name": "vmss-devops-agent",
        "version": "0.2.6",
        "provider": "azurerm",
        "provider_logo_url": "/images/providers/azure.png?3",
        "description": "Terraform Azure DevOps virtual machine scale set agent module ",
        "source": "https://github.com/tonyskidmore/terraform-azurerm-vmss-devops-agent",
        "tag": "v0.2.6",
        "published_at": "2023-09-10T19:13:06.287953Z",
        "downloads": 3064,
        "verified": false
    },
    {
        "id": "samygitrepo/staticwebsitepublic/azurerm/2.0.0",
        "owner": "",
        "namespace": "samygitrepo",
        "name": "staticwebsitepublic",
        "version": "2.0.0",
        "provider": "azurerm",
        "provider_logo_url": "/images/providers/azure.png?3",
        "description": "Terraform Modules to be shared in Terraform Public Registry",
        "source": "https://github.com/samygitrepo/terraform-azurerm-staticwebsitepublic",
        "tag": "2.0.0",
        "published_at": "2023-01-06T00:38:34.031919Z",
        "downloads": 1495,
        "verified": false
    },
    {
        "id": "GoogleCloudPlatform/cloud-workflows/google/0.1.1",
        "owner": "",
        "namespace": "GoogleCloudPlatform",
        "name": "cloud-workflows",
        "version": "0.1.1",
        "provider": "google",
        "provider_logo_url": "/images/providers/google-cloud.svg",
        "description": "Manage Workflows with optional Scheduler or Event Arc triggers",
        "source": "https://github.com/GoogleCloudPlatform/terraform-google-cloud-workflows",
        "tag": "v0.1.1",
        "published_at": "2023-12-07T16:24:17.53662Z",
        "downloads": 6184,
        "verified": false
    },
    {
        "id": "netskopeoss/azure/netskopebwan/0.0.1",
        "owner": "",
        "namespace": "netskopeoss",
        "name": "azure",
        "version": "0.0.1",
        "provider": "netskopebwan",
        "provider_logo_url": "/images/providers/generic.svg?2",
        "description": "",
        "source": "https://github.com/netskopeoss/terraform-netskopebwan-azure",
        "tag": "v0.0.1",
        "published_at": "2023-01-06T06:36:54.882492Z",
        "downloads": 1,
        "verified": false
    },
    {
        "id": "netskopeoss/aws/netskopebwan/0.0.1",
        "owner": "",
        "namespace": "netskopeoss",
        "name": "aws",
        "version": "0.0.1",
        "provider": "netskopebwan",
        "provider_logo_url": "/images/providers/generic.svg?2",
        "description": "",
        "source": "https://github.com/netskopeoss/terraform-netskopebwan-aws",
        "tag": "v0.0.1",
        "published_at": "2023-01-06T06:44:37.764756Z",
        "downloads": 0,
        "verified": false
    },
    {
        "id": "netskopeoss/gcp/netskopebwan/0.0.1",
        "owner": "",
        "namespace": "netskopeoss",
        "name": "gcp",
        "version": "0.0.1",
        "provider": "netskopebwan",
        "provider_logo_url": "/images/providers/generic.svg?2",
        "description": "",
        "source": "https://github.com/netskopeoss/terraform-netskopebwan-gcp",
        "tag": "v0.0.1",
        "published_at": "2023-01-06T06:44:52.128347Z",
        "downloads": 0,
        "verified": false
    },
    {
        "id": "data-platform-hq/debezium/azurerm/1.0.5",
        "owner": "",
        "namespace": "data-platform-hq",
        "name": "debezium",
        "version": "1.0.5",
        "provider": "azurerm",
        "provider_logo_url": "/images/providers/azure.png?3",
        "description": "Terraform module for Debezium provisioning using Azure Container Instance",
        "source": "https://github.com/data-platform-hq/terraform-azurerm-debezium",
        "tag": "v1.0.5",
        "published_at": "2023-02-02T08:34:41.500816Z",
        "downloads": 5492,
        "verified": false
    },
    {
        "id": "bschaatsbergen/atlantis/gce/4.1.0",
        "owner": "",
        "namespace": "bschaatsbergen",
        "name": "atlantis",
        "version": "4.1.0",
        "provider": "gce",
        "provider_logo_url": "/images/providers/generic.svg?2",
        "description": "A set of  Terraform configurations for running Atlantis on @googlecloud Compute Engine",
        "source": "https://github.com/bschaatsbergen/terraform-gce-atlantis",
        "tag": "4.1.0",
        "published_at": "2024-03-28T20:45:19.037624Z",
        "downloads": 4291,
        "verified": false
    },
    {
        "id": "netascode/pim-policy/aci/0.3.0",
        "owner": "",
        "namespace": "netascode",
        "name": "pim-policy",
        "version": "0.3.0",
        "provider": "aci",
        "provider_logo_url": "/images/providers/generic.svg?2",
        "description": "Terraform Cisco ACI PIM Policy Module ",
        "source": "https://github.com/netascode/terraform-aci-pim-policy",
        "tag": "v0.3.0",
        "published_at": "2024-01-12T13:48:33.845539Z",
        "downloads": 11137,
        "verified": false
    },
    {
        "id": "netascode/fabric-span-destination-group/aci/0.3.0",
        "owner": "",
        "namespace": "netascode",
        "name": "fabric-span-destination-group",
        "version": "0.3.0",
        "provider": "aci",
        "provider_logo_url": "/images/providers/generic.svg?2",
        "description": "Terraform Cisco ACI Fabric SPAN Destination Group Module",
        "source": "https://github.com/netascode/terraform-aci-fabric-span-destination-group",
        "tag": "v0.3.0",
        "published_at": "2024-01-12T13:47:18.760575Z",
        "downloads": 9721,
        "verified": false
    },
    {
        "id": "netascode/fabric-span-source-group/aci/0.3.0",
        "owner": "",
        "namespace": "netascode",
        "name": "fabric-span-source-group",
        "version": "0.3.0",
        "provider": "aci",
        "provider_logo_url": "/images/providers/generic.svg?2",
        "description": "Terraform Cisco ACI Fabric SPAN Source Group Module",
        "source": "https://github.com/netascode/terraform-aci-fabric-span-source-group",
        "tag": "v0.3.0",
        "published_at": "2024-01-12T13:47:18.445823Z",
        "downloads": 9681,
        "verified": false
    },
    {
        "id": "telia-oss/vapp/vcd/1.4.0",
        "owner": "",
        "namespace": "telia-oss",
        "name": "vapp",
        "version": "1.4.0",
        "provider": "vcd",
        "provider_logo_url": "/images/providers/generic.svg?2",
        "description": "",
        "source": "https://github.com/telia-oss/terraform-vcd-vapp",
        "tag": "v1.4.0",
        "published_at": "2023-02-20T11:35:51.213813Z",
        "downloads": 40,
        "verified": false
    },
    {
        "id": "clouddrove/vpn/azure/1.0.2",
        "owner": "",
        "namespace": "clouddrove",
        "name": "vpn",
        "version": "1.0.2",
        "provider": "azure",
        "provider_logo_url": "/images/providers/azure.png?3",
        "description": "This terraform module is designed to create Azure VPN resources. Azure VPN Gateway is a service that uses a specific type of virtual network gateway to send encrypted traffic between an Azure virtual network and on-premises locations over the public Internet. You can also use VPN Gateway to send encrypted traffic between Azure virtual networks .",
        "source": "https://github.com/clouddrove/terraform-azure-vpn",
        "tag": "1.0.2",
        "published_at": "2023-07-03T16:48:49.341249Z",
        "downloads": 1526,
        "verified": false
    },
    {
        "id": "clouddrove/vnet-peering/azure/1.0.1",
        "owner": "",
        "namespace": "clouddrove",
        "name": "vnet-peering",
        "version": "1.0.1",
        "provider": "azure",
        "provider_logo_url": "/images/providers/azure.png?3",
        "description": "",
        "source": "https://github.com/clouddrove/terraform-azure-vnet-peering",
        "tag": "1.0.1",
        "published_at": "2023-04-27T09:22:06.226245Z",
        "downloads": 1527,
        "verified": false
    },
    {
        "id": "plus3it/org-new-account-delete-default-vpcs/aws/1.1.1",
        "owner": "",
        "namespace": "plus3it",
        "name": "org-new-account-delete-default-vpcs",
        "version": "1.1.1",
        "provider": "aws",
        "provider_logo_url": "/images/providers/aws.png",
        "description": "Terraform module for a lambda function that deletes default VPCs in all regions when an account is added to an AWS Organization",
        "source": "https://github.com/plus3it/terraform-aws-org-new-account-delete-default-vpcs",
        "tag": "1.1.1",
        "published_at": "2023-04-18T21:08:34.698504Z",
        "downloads": 0,
        "verified": false
    },
    {
        "id": "GoCarrot/rds_alerts/aws/0.1.0",
        "owner": "",
        "namespace": "GoCarrot",
        "name": "rds_alerts",
        "version": "0.1.0",
        "provider": "aws",
        "provider_logo_url": "/images/providers/aws.png",
        "description": "",
        "source": "https://github.com/GoCarrot/terraform-aws-rds_alerts",
        "tag": "v0.1.0",
        "published_at": "2023-01-07T01:00:04.511337Z",
        "downloads": 1550,
        "verified": false
    },
    {
        "id": "GoCarrot/circleci_oidc/aws/0.1.2",
        "owner": "",
        "namespace": "GoCarrot",
        "name": "circleci_oidc",
        "version": "0.1.2",
        "provider": "aws",
        "provider_logo_url": "/images/providers/aws.png",
        "description": "A terraform module to create a CircleCI OIDC provider in AWS IAM.",
        "source": "https://github.com/GoCarrot/terraform-aws-circleci_oidc",
        "tag": "v0.1.2",
        "published_at": "2023-12-09T01:54:39.070421Z",
        "downloads": 13154,
        "verified": false
    },
    {
        "id": "timo-reymann/aws-apigateway-swagger-ui/module/1.5.2",
        "owner": "",
        "namespace": "timo-reymann",
        "name": "aws-apigateway-swagger-ui",
        "version": "1.5.2",
        "provider": "module",
        "provider_logo_url": "/images/providers/generic.svg?2",
        "description": "Serve Swagger documentation right from your API-Gateway.",
        "source": "https://github.com/timo-reymann/terraform-module-aws-apigateway-swagger-ui",
        "tag": "1.5.2",
        "published_at": "2023-12-04T17:16:12.596225Z",
        "downloads": 689,
        "verified": false
    },
    {
        "id": "GowdamTF/staticwebsitepublic/azurerm/2.0.0",
        "owner": "",
        "namespace": "GowdamTF",
        "name": "staticwebsitepublic",
        "version": "2.0.0",
        "provider": "azurerm",
        "provider_logo_url": "/images/providers/azure.png?3",
        "description": "Myteststaticwebsitepublic for DEMO",
        "source": "https://github.com/GowdamTF/terraform-azurerm-staticwebsitepublic",
        "tag": "2.0.0",
        "published_at": "2023-01-07T17:06:24.638852Z",
        "downloads": 1486,
        "verified": false
    },
    {
        "id": "Tom01098/minecraft/aws/1.0.0",
        "owner": "",
        "namespace": "Tom01098",
        "name": "minecraft",
        "version": "1.0.0",
        "provider": "aws",
        "provider_logo_url": "/images/providers/aws.png",
        "description": "Create a Minecraft server running on AWS EC2",
        "source": "https://github.com/Tom01098/terraform-aws-minecraft",
        "tag": "1.0.0",
        "published_at": "2023-01-07T20:15:08.816758Z",
        "downloads": 1387,
        "verified": false
    },
    {
        "id": "eeyoontaek/inventory/ansible/0.1.6",
        "owner": "",
        "namespace": "eeyoontaek",
        "name": "inventory",
        "version": "0.1.6",
        "provider": "ansible",
        "provider_logo_url": "/images/providers/generic.svg?2",
        "description": "",
        "source": "https://github.com/eeyoontaek/terraform-ansible-inventory",
        "tag": "0.1.6",
        "published_at": "2023-01-09T01:57:24.738813Z",
        "downloads": 42,
        "verified": false
    },
    {
        "id": "vnisolutions/aurora/aws/1.2.0",
        "owner": "",
        "namespace": "vnisolutions",
        "name": "aurora",
        "version": "1.2.0",
        "provider": "aws",
        "provider_logo_url": "/images/providers/aws.png",
        "description": "",
        "source": "https://github.com/vnisolutions/terraform-aws-aurora",
        "tag": "v1.2.0",
        "published_at": "2023-11-28T02:31:20.638158Z",
        "downloads": 1535,
        "verified": false
    },
    {
        "id": "vnisolutions/rds/aws/1.0.0",
        "owner": "",
        "namespace": "vnisolutions",
        "name": "rds",
        "version": "1.0.0",
        "provider": "aws",
        "provider_logo_url": "/images/providers/aws.png",
        "description": "",
        "source": "https://github.com/vnisolutions/terraform-aws-rds",
        "tag": "v1.0.0",
        "published_at": "2023-01-08T08:06:31.471561Z",
        "downloads": 1499,
        "verified": false
    },
    {
        "id": "keidarcy/vpc/aws/1.0.0",
        "owner": "",
        "namespace": "keidarcy",
        "name": "vpc",
        "version": "1.0.0",
        "provider": "aws",
        "provider_logo_url": "/images/providers/aws.png",
        "description": "",
        "source": "https://github.com/keidarcy/terraform-aws-vpc",
        "tag": "v1.0.0",
        "published_at": "2023-01-09T00:44:47.934744Z",
        "downloads": 1490,
        "verified": false
    },
    {
        "id": "flaudisio/elasticache/aws/0.1.1",
        "owner": "",
        "namespace": "flaudisio",
        "name": "elasticache",
        "version": "0.1.1",
        "provider": "aws",
        "provider_logo_url": "/images/providers/aws.png",
        "description": "Modules for deploying and managing ElastiCache resources on AWS.",
        "source": "https://github.com/flaudisio/terraform-aws-elasticache",
        "tag": "v0.1.1",
        "published_at": "2023-01-09T03:15:57.786912Z",
        "downloads": 1527,
        "verified": false
    },
    {
        "id": "voquis/groups-projects/gitlab/0.0.1",
        "owner": "",
        "namespace": "voquis",
        "name": "groups-projects",
        "version": "0.0.1",
        "provider": "gitlab",
        "provider_logo_url": "/images/providers/generic.svg?2",
        "description": "",
        "source": "https://github.com/voquis/terraform-gitlab-groups-projects",
        "tag": "0.0.1",
        "published_at": "2023-01-09T03:36:42.703098Z",
        "downloads": 3,
        "verified": false
    },
    {
        "id": "clouddrove/network-security-group/azure/1.0.4",
        "owner": "",
        "namespace": "clouddrove",
        "name": "network-security-group",
        "version": "1.0.4",
        "provider": "azure",
        "provider_logo_url": "/images/providers/azure.png?3",
        "description": " A Terraform module to create NETWORK SECURITY GROUP resource on AZURE. ",
        "source": "https://github.com/clouddrove/terraform-azure-network-security-group",
        "tag": "1.0.4",
        "published_at": "2023-06-20T07:08:21.521044Z",
        "downloads": 2838,
        "verified": false
    },
    {
        "id": "cloudprodigy/ecs/aws/2.0.3",
        "owner": "",
        "namespace": "cloudprodigy",
        "name": "ecs",
        "version": "2.0.3",
        "provider": "aws",
        "provider_logo_url": "/images/providers/aws.png",
        "description": "Build ECS Cluster, Application Load Balancer, CodePipeline, CodeBuild, CloudWatch Log Groups, EFS and ECS Service Discovery on AWS using Terraform",
        "source": "https://github.com/cloudprodigy/terraform-aws-ecs",
        "tag": "v2.0.3",
        "published_at": "2023-01-23T12:32:55.863655Z",
        "downloads": 0,
        "verified": false
    },
    {
        "id": "lukalapulakshman123/llrtest/aws/0.0.3",
        "owner": "",
        "namespace": "lukalapulakshman123",
        "name": "llrtest",
        "version": "0.0.3",
        "provider": "aws",
        "provider_logo_url": "/images/providers/aws.png",
        "description": "",
        "source": "https://github.com/lukalapulakshman123/terraform-aws-llrtest",
        "tag": "v0.0.3",
        "published_at": "2023-01-22T14:58:33.302737Z",
        "downloads": 1493,
        "verified": false
    },
    {
        "id": "asajoshi/storageaccount/azurerm/1.0.0",
        "owner": "",
        "namespace": "asajoshi",
        "name": "storageaccount",
        "version": "1.0.0",
        "provider": "azurerm",
        "provider_logo_url": "/images/providers/azure.png?3",
        "description": "This contains terraform code for creating storage account module with private endpoint",
        "source": "https://github.com/asajoshi/terraform-azurerm-storageaccount",
        "tag": "v1.0.0",
        "published_at": "2023-01-09T15:24:53.175508Z",
        "downloads": 0,
        "verified": false
    }
]
