[
    {
        "id": "hm-keles/docker-ec2-instance/aws/0.0.1",
        "owner": "",
        "namespace": "hm-keles",
        "name": "docker-ec2-instance",
        "version": "0.0.1",
        "provider": "aws",
        "provider_logo_url": "/images/providers/aws.png",
        "description": "",
        "source": "https://github.com/hm-keles/terraform-aws-docker-ec2-instance",
        "tag": "v0.0.1",
        "published_at": "2022-10-27T12:41:18.742266Z",
        "downloads": 1717,
        "verified": false
    },
    {
        "id": "Dugera27/waf-webaclv2/aws/1.0.1",
        "owner": "",
        "namespace": "Dugera27",
        "name": "waf-webaclv2",
        "version": "1.0.1",
        "provider": "aws",
        "provider_logo_url": "/images/providers/aws.png",
        "description": "Terraform module to configure WAF V2 Web ACL with managed rules for Application Load Balancer",
        "source": "https://github.com/Dugera27/terraform-aws-waf-webaclv2",
        "tag": "v1.0.1",
        "published_at": "2022-12-22T12:10:48.515464Z",
        "downloads": 1804,
        "verified": false
    },
    {
        "id": "terraform-pingidentity-modules/davinci-connection/pingone/0.0.1",
        "owner": "",
        "namespace": "terraform-pingidentity-modules",
        "name": "davinci-connection",
        "version": "0.0.1",
        "provider": "pingone",
        "provider_logo_url": "/images/providers/generic.svg?2",
        "description": "Ping Identity PingOne DaVinci modules to manage connections",
        "source": "https://github.com/terraform-pingidentity-modules/terraform-pingone-davinci-connection",
        "tag": "v0.0.1",
        "published_at": "2022-10-27T16:28:50.569391Z",
        "downloads": 8028,
        "verified": false
    },
    {
        "id": "skyfjell/iam-ci-cd/aws/0.0.1",
        "owner": "",
        "namespace": "skyfjell",
        "name": "iam-ci-cd",
        "version": "0.0.1",
        "provider": "aws",
        "provider_logo_url": "/images/providers/aws.png",
        "description": "IAM Configuration for Terraform CI/CD Integration",
        "source": "https://github.com/skyfjell/terraform-aws-iam-ci-cd",
        "tag": "0.0.1",
        "published_at": "2022-10-27T18:01:13.814015Z",
        "downloads": 0,
        "verified": false
    },
    {
        "id": "skyfjell/s3-backend/aws/0.0.1",
        "owner": "",
        "namespace": "skyfjell",
        "name": "s3-backend",
        "version": "0.0.1",
        "provider": "aws",
        "provider_logo_url": "/images/providers/aws.png",
        "description": "Create Terraform Backends in S3",
        "source": "https://github.com/skyfjell/terraform-aws-s3-backend",
        "tag": "0.0.1",
        "published_at": "2022-10-27T18:01:33.912289Z",
        "downloads": 0,
        "verified": false
    },
    {
        "id": "rallyware/ssh-key-pair/tls/0.1.1",
        "owner": "",
        "namespace": "rallyware",
        "name": "ssh-key-pair",
        "version": "0.1.1",
        "provider": "tls",
        "provider_logo_url": "/images/providers/generic.svg?2",
        "description": "A simple terraform module for generating SSH key-pair",
        "source": "https://github.com/rallyware/terraform-tls-ssh-key-pair",
        "tag": "0.1.1",
        "published_at": "2022-11-04T15:59:12.159594Z",
        "downloads": 28,
        "verified": false
    },
    {
        "id": "dasmeta/iam/aws/1.0.4",
        "owner": "",
        "namespace": "dasmeta",
        "name": "iam",
        "version": "1.0.4",
        "provider": "aws",
        "provider_logo_url": "/images/providers/aws.png",
        "description": "Terraform modules managing AWS IAM resources",
        "source": "https://github.com/dasmeta/terraform-aws-iam",
        "tag": "v1.0.4",
        "published_at": "2024-05-13T11:16:59.196942Z",
        "downloads": 2147,
        "verified": false
    },
    {
        "id": "vihuo/s3backend/aws/0.1.5",
        "owner": "",
        "namespace": "vihuo",
        "name": "s3backend",
        "version": "0.1.5",
        "provider": "aws",
        "provider_logo_url": "/images/providers/aws.png",
        "description": "",
        "source": "https://github.com/vihuo/terraform-aws-s3backend",
        "tag": "v0.1.5",
        "published_at": "2022-10-28T12:58:20.091399Z",
        "downloads": 1713,
        "verified": false
    },
    {
        "id": "dtoch56/dns/yandex/0.0.1",
        "owner": "",
        "namespace": "dtoch56",
        "name": "dns",
        "version": "0.0.1",
        "provider": "yandex",
        "provider_logo_url": "/images/providers/generic.svg?2",
        "description": "DNS module",
        "source": "https://github.com/dtoch56/terraform-yandex-dns",
        "tag": "v0.0.1",
        "published_at": "2022-10-28T15:11:47.810689Z",
        "downloads": 2,
        "verified": false
    },
    {
        "id": "bayupw/csr1000v-self-configured/equinix/1.0.0",
        "owner": "",
        "namespace": "bayupw",
        "name": "csr1000v-self-configured",
        "version": "1.0.0",
        "provider": "equinix",
        "provider_logo_url": "/images/providers/generic.svg?2",
        "description": "Terraform module for deploying a Self-Configured BYOL Cisco CSR 1000V router in Equinix Fabric.",
        "source": "https://github.com/bayupw/terraform-equinix-csr1000v-self-configured",
        "tag": "v1.0.0",
        "published_at": "2022-10-31T17:12:56.581459Z",
        "downloads": 5,
        "verified": false
    },
    {
        "id": "djangoflow/velero/google/1.0.3",
        "owner": "",
        "namespace": "djangoflow",
        "name": "velero",
        "version": "1.0.3",
        "provider": "google",
        "provider_logo_url": "/images/providers/google-cloud.svg",
        "description": "Opinionated Velero deployment to Google GKE/GCS",
        "source": "https://github.com/djangoflow/terraform-google-velero",
        "tag": "1.0.3",
        "published_at": "2022-10-31T11:22:04.705176Z",
        "downloads": 1662,
        "verified": false
    },
    {
        "id": "artonjashari/user-arton-modulee/iam/1.0.2",
        "owner": "",
        "namespace": "artonjashari",
        "name": "user-arton-modulee",
        "version": "1.0.2",
        "provider": "iam",
        "provider_logo_url": "/images/providers/generic.svg?2",
        "description": "",
        "source": "https://github.com/artonjashari/terraform-iam-user-arton-modulee",
        "tag": "v1.0.2",
        "published_at": "2022-11-05T13:42:32.355273Z",
        "downloads": 0,
        "verified": false
    },
    {
        "id": "woodonggyu/cloudtrail/aws/1.2.2",
        "owner": "",
        "namespace": "woodonggyu",
        "name": "cloudtrail",
        "version": "1.2.2",
        "provider": "aws",
        "provider_logo_url": "/images/providers/aws.png",
        "description": "Terraform module which creates AWS CloudTrail.",
        "source": "https://github.com/woodonggyu/terraform-aws-cloudtrail",
        "tag": "v1.2.2",
        "published_at": "2022-11-09T13:26:37.553627Z",
        "downloads": 1710,
        "verified": false
    },
    {
        "id": "axetrading/short-name/null/1.0.0",
        "owner": "",
        "namespace": "axetrading",
        "name": "short-name",
        "version": "1.0.0",
        "provider": "null",
        "provider_logo_url": "/images/providers/generic.svg?2",
        "description": "Module for truncating strings in a stable way",
        "source": "https://github.com/axetrading/terraform-null-short-name",
        "tag": "v1.0.0",
        "published_at": "2022-10-29T22:10:34.903335Z",
        "downloads": 6473,
        "verified": false
    },
    {
        "id": "tonyskidmore/vmss/azurerm/0.4.0",
        "owner": "",
        "namespace": "tonyskidmore",
        "name": "vmss",
        "version": "0.4.0",
        "provider": "azurerm",
        "provider_logo_url": "/images/providers/azure.png?3",
        "description": "Terraform azurerm Virtual Machine Scale Set module",
        "source": "https://github.com/tonyskidmore/terraform-azurerm-vmss",
        "tag": "v0.4.0",
        "published_at": "2023-12-02T14:01:11.595687Z",
        "downloads": 4419,
        "verified": false
    },
    {
        "id": "shadbury/patching/aws/1.0.0",
        "owner": "",
        "namespace": "shadbury",
        "name": "patching",
        "version": "1.0.0",
        "provider": "aws",
        "provider_logo_url": "/images/providers/aws.png",
        "description": "",
        "source": "https://github.com/shadbury/terraform-aws-patching",
        "tag": "1.0.0",
        "published_at": "2022-10-31T04:29:54.208098Z",
        "downloads": 1889,
        "verified": false
    },
    {
        "id": "bootlabstech/pubsub/google/1.0.9",
        "owner": "",
        "namespace": "bootlabstech",
        "name": "pubsub",
        "version": "1.0.9",
        "provider": "google",
        "provider_logo_url": "/images/providers/google-cloud.svg",
        "description": "Creates a Pub-Sub schema, Topic and Subscription.",
        "source": "https://github.com/bootlabstech/terraform-google-pubsub",
        "tag": "v1.0.9",
        "published_at": "2024-06-10T07:59:22.973256Z",
        "downloads": 2753,
        "verified": false
    },
    {
        "id": "heisinbug/user/pagerduty/1.0.0",
        "owner": "",
        "namespace": "heisinbug",
        "name": "user",
        "version": "1.0.0",
        "provider": "pagerduty",
        "provider_logo_url": "/images/providers/generic.svg?2",
        "description": "A terraform module to create multiple users with JSON",
        "source": "https://github.com/heisinbug/terraform-pagerduty-user",
        "tag": "v1.0.0",
        "published_at": "2022-10-31T09:47:52.970116Z",
        "downloads": 0,
        "verified": false
    },
    {
        "id": "so1omon563/rds-instance/aws/1.0.2",
        "owner": "",
        "namespace": "so1omon563",
        "name": "rds-instance",
        "version": "1.0.2",
        "provider": "aws",
        "provider_logo_url": "/images/providers/aws.png",
        "description": "Create an RDS instance with most common options.",
        "source": "https://github.com/so1omon563/terraform-aws-rds-instance",
        "tag": "v1.0.2",
        "published_at": "2023-03-14T19:37:17.540569Z",
        "downloads": 1715,
        "verified": false
    },
    {
        "id": "cloudposse/network-firewall/aws/0.3.2",
        "owner": "",
        "namespace": "cloudposse",
        "name": "network-firewall",
        "version": "0.3.2",
        "provider": "aws",
        "provider_logo_url": "/images/providers/aws.png",
        "description": "Terraform module to provision and manage AWS Network Firewall resources",
        "source": "https://github.com/cloudposse/terraform-aws-network-firewall",
        "tag": "0.3.2",
        "published_at": "2023-01-31T22:16:00.102603Z",
        "downloads": 8489,
        "verified": false
    },
    {
        "id": "asumankamberoglu/docker-instance/aws/0.0.1",
        "owner": "",
        "namespace": "asumankamberoglu",
        "name": "docker-instance",
        "version": "0.0.1",
        "provider": "aws",
        "provider_logo_url": "/images/providers/aws.png",
        "description": "Terraform module which creates a docker instance resource on AWS",
        "source": "https://github.com/asumankamberoglu/terraform-aws-docker-instance",
        "tag": "v0.0.01",
        "published_at": "2022-11-08T19:21:23.999695Z",
        "downloads": 1705,
        "verified": false
    },
    {
        "id": "HashiHinch/s3-bucket/aws/3.5.0",
        "owner": "",
        "namespace": "HashiHinch",
        "name": "s3-bucket",
        "version": "3.5.0",
        "provider": "aws",
        "provider_logo_url": "/images/providers/aws.png",
        "description": "Terraform module which creates S3 bucket resources on AWS \ud83c\uddfa\ud83c\udde6",
        "source": "https://github.com/HashiHinch/terraform-aws-s3-bucket",
        "tag": "v3.5.0",
        "published_at": "2022-10-31T23:04:49.389788Z",
        "downloads": 1708,
        "verified": false
    },
    {
        "id": "popravak/rg/azurerm/1.0.3",
        "owner": "",
        "namespace": "popravak",
        "name": "rg",
        "version": "1.0.3",
        "provider": "azurerm",
        "provider_logo_url": "/images/providers/azure.png?3",
        "description": "Azure resource group creation with Terraform",
        "source": "https://github.com/popravak/terraform-azurerm-rg",
        "tag": "1.0.3",
        "published_at": "2022-11-05T08:47:22.209151Z",
        "downloads": 1794,
        "verified": false
    },
    {
        "id": "popravak/vnet/azurerm/1.0.4",
        "owner": "",
        "namespace": "popravak",
        "name": "vnet",
        "version": "1.0.4",
        "provider": "azurerm",
        "provider_logo_url": "/images/providers/azure.png?3",
        "description": "Basic Azure virtual network w/o NSGs",
        "source": "https://github.com/popravak/terraform-azurerm-vnet",
        "tag": "1.0.4",
        "published_at": "2022-11-05T08:52:53.648546Z",
        "downloads": 1786,
        "verified": false
    },
    {
        "id": "divlv/vm/divlv/2.0.1",
        "owner": "",
        "namespace": "divlv",
        "name": "vm",
        "version": "2.0.1",
        "provider": "divlv",
        "provider_logo_url": "/images/providers/generic.svg?2",
        "description": "Terraform module for Azure Virtula machine",
        "source": "https://github.com/divlv/terraform-divlv-vm",
        "tag": "v2.0.1",
        "published_at": "2024-01-16T10:37:42.859209Z",
        "downloads": 18,
        "verified": false
    },
    {
        "id": "tonyskidmore/azure-devops-elasticpool/shell/0.4.4",
        "owner": "",
        "namespace": "tonyskidmore",
        "name": "azure-devops-elasticpool",
        "version": "0.4.4",
        "provider": "shell",
        "provider_logo_url": "/images/providers/generic.svg?2",
        "description": "Terraform Azure DevOps Scale Set Agent module",
        "source": "https://github.com/tonyskidmore/terraform-shell-azure-devops-elasticpool",
        "tag": "v0.4.4",
        "published_at": "2023-01-28T16:22:59.750932Z",
        "downloads": 2721,
        "verified": false
    },
    {
        "id": "terraform-cisco-modules/access/aci/3.1.11",
        "owner": "",
        "namespace": "terraform-cisco-modules",
        "name": "access",
        "version": "3.1.11",
        "provider": "aci",
        "provider_logo_url": "/images/providers/generic.svg?2",
        "description": "Terraform - ACI > Access Module",
        "source": "https://github.com/terraform-cisco-modules/terraform-aci-access",
        "tag": "v3.1.11",
        "published_at": "2024-05-03T14:42:22.434968Z",
        "downloads": 1150,
        "verified": false
    },
    {
        "id": "terraform-cisco-modules/admin/aci/3.1.11",
        "owner": "",
        "namespace": "terraform-cisco-modules",
        "name": "admin",
        "version": "3.1.11",
        "provider": "aci",
        "provider_logo_url": "/images/providers/generic.svg?2",
        "description": "Terraform - ACI > Admin Module",
        "source": "https://github.com/terraform-cisco-modules/terraform-aci-admin",
        "tag": "v3.1.11",
        "published_at": "2024-05-03T14:42:24.17573Z",
        "downloads": 1378,
        "verified": false
    },
    {
        "id": "terraform-cisco-modules/fabric/aci/3.1.11",
        "owner": "",
        "namespace": "terraform-cisco-modules",
        "name": "fabric",
        "version": "3.1.11",
        "provider": "aci",
        "provider_logo_url": "/images/providers/generic.svg?2",
        "description": "Terraform - ACI > Fabric Module",
        "source": "https://github.com/terraform-cisco-modules/terraform-aci-fabric",
        "tag": "v3.1.11",
        "published_at": "2024-05-03T14:42:24.47708Z",
        "downloads": 1414,
        "verified": false
    },
    {
        "id": "terraform-cisco-modules/switch/aci/3.1.11",
        "owner": "",
        "namespace": "terraform-cisco-modules",
        "name": "switch",
        "version": "3.1.11",
        "provider": "aci",
        "provider_logo_url": "/images/providers/generic.svg?2",
        "description": "Terraform - ACI > Switch Configuration Module",
        "source": "https://github.com/terraform-cisco-modules/terraform-aci-switch",
        "tag": "v3.1.11",
        "published_at": "2024-05-03T14:42:24.625456Z",
        "downloads": 1384,
        "verified": false
    },
    {
        "id": "terraform-cisco-modules/system-settings/aci/3.1.11",
        "owner": "",
        "namespace": "terraform-cisco-modules",
        "name": "system-settings",
        "version": "3.1.11",
        "provider": "aci",
        "provider_logo_url": "/images/providers/generic.svg?2",
        "description": "Terraform - ACI > System Settings Module",
        "source": "https://github.com/terraform-cisco-modules/terraform-aci-system-settings",
        "tag": "v3.1.11",
        "published_at": "2024-05-03T14:42:25.924452Z",
        "downloads": 1389,
        "verified": false
    },
    {
        "id": "terraform-cisco-modules/tenants/aci/3.1.11",
        "owner": "",
        "namespace": "terraform-cisco-modules",
        "name": "tenants",
        "version": "3.1.11",
        "provider": "aci",
        "provider_logo_url": "/images/providers/generic.svg?2",
        "description": "Terraform - ACI > Tenant Module",
        "source": "https://github.com/terraform-cisco-modules/terraform-aci-tenants",
        "tag": "v3.1.11",
        "published_at": "2024-05-03T14:42:26.603202Z",
        "downloads": 1586,
        "verified": false
    },
    {
        "id": "terraform-pingidentity-modules/sso-application/pingone/0.0.6",
        "owner": "",
        "namespace": "terraform-pingidentity-modules",
        "name": "sso-application",
        "version": "0.0.6",
        "provider": "pingone",
        "provider_logo_url": "/images/providers/generic.svg?2",
        "description": "Ping Identity PingOne module to manage applications",
        "source": "https://github.com/terraform-pingidentity-modules/terraform-pingone-sso-application",
        "tag": "v0.0.6",
        "published_at": "2022-11-07T12:00:36.494528Z",
        "downloads": 173,
        "verified": false
    },
    {
        "id": "adamwshero/api-gateway/aws/1.2.0",
        "owner": "",
        "namespace": "adamwshero",
        "name": "api-gateway",
        "version": "1.2.0",
        "provider": "aws",
        "provider_logo_url": "/images/providers/aws.png",
        "description": "Terragrunt friendly module to create AWS API Gateway (V1) w\\Optional WAF, many stages/api keys/usage plans using the OpenAPI 3.x spec. \ud83c\uddfa\ud83c\udde6",
        "source": "https://github.com/adamwshero/terraform-aws-api-gateway",
        "tag": "1.2.0",
        "published_at": "2023-11-17T23:55:01.164016Z",
        "downloads": 2339,
        "verified": false
    },
    {
        "id": "popravak/linuxvm/azurerm/1.0.3",
        "owner": "",
        "namespace": "popravak",
        "name": "linuxvm",
        "version": "1.0.3",
        "provider": "azurerm",
        "provider_logo_url": "/images/providers/azure.png?3",
        "description": "Azure linux virtual machine",
        "source": "https://github.com/popravak/terraform-azurerm-linuxvm",
        "tag": "1.0.3",
        "published_at": "2022-11-06T18:33:10.728044Z",
        "downloads": 1692,
        "verified": false
    },
    {
        "id": "atcomputing/lb-http-tutorial/azurerm/0.0.10",
        "owner": "",
        "namespace": "atcomputing",
        "name": "lb-http-tutorial",
        "version": "0.0.10",
        "provider": "azurerm",
        "provider_logo_url": "/images/providers/azure.png?3",
        "description": "A module to create a http load balancer in azure for the terraform training ",
        "source": "https://github.com/atcomputing/terraform-azurerm-lb-http-tutorial",
        "tag": "v0.0.10",
        "published_at": "2023-09-08T13:51:46.425647Z",
        "downloads": 1992,
        "verified": false
    },
    {
        "id": "dasmeta/rds/aws/1.3.5",
        "owner": "",
        "namespace": "dasmeta",
        "name": "rds",
        "version": "1.3.5",
        "provider": "aws",
        "provider_logo_url": "/images/providers/aws.png",
        "description": "Terraform Aws RDS module",
        "source": "https://github.com/dasmeta/terraform-aws-rds",
        "tag": "v1.3.5",
        "published_at": "2024-05-06T11:36:27.82884Z",
        "downloads": 1986,
        "verified": false
    },
    {
        "id": "truemark/rds-postgres/aws/1.0.3",
        "owner": "",
        "namespace": "truemark",
        "name": "rds-postgres",
        "version": "1.0.3",
        "provider": "aws",
        "provider_logo_url": "/images/providers/aws.png",
        "description": "",
        "source": "https://github.com/truemark/terraform-aws-rds-postgres",
        "tag": "v1.0.3",
        "published_at": "2024-06-10T17:39:57.228626Z",
        "downloads": 1786,
        "verified": false
    },
    {
        "id": "so1omon563/ecs-container-definition/aws/2.0.4",
        "owner": "",
        "namespace": "so1omon563",
        "name": "ecs-container-definition",
        "version": "2.0.4",
        "provider": "aws",
        "provider_logo_url": "/images/providers/aws.png",
        "description": "Module to create a container definition for ECS in a Terraform friendly way.",
        "source": "https://github.com/so1omon563/terraform-aws-ecs-container-definition",
        "tag": "v2.0.4",
        "published_at": "2023-03-14T19:14:58.391152Z",
        "downloads": 1727,
        "verified": false
    },
    {
        "id": "truemark/bastion/aws/1.0.1",
        "owner": "",
        "namespace": "truemark",
        "name": "bastion",
        "version": "1.0.1",
        "provider": "aws",
        "provider_logo_url": "/images/providers/aws.png",
        "description": "Stands up a basic bastion EC2 instance",
        "source": "https://github.com/truemark/terraform-aws-bastion",
        "tag": "v1.0.1",
        "published_at": "2024-06-12T17:52:30.422959Z",
        "downloads": 2266,
        "verified": false
    },
    {
        "id": "IamTheFij/levant/nomad/0.1.0",
        "owner": "",
        "namespace": "IamTheFij",
        "name": "levant",
        "version": "0.1.0",
        "provider": "nomad",
        "provider_logo_url": "/images/providers/nomad.svg?3",
        "description": "A Levant render module for Terraform ",
        "source": "https://github.com/IamTheFij/terraform-nomad-levant",
        "tag": "v0.1.0",
        "published_at": "2022-11-02T17:45:54.168093Z",
        "downloads": 20,
        "verified": false
    },
    {
        "id": "truemark/rds-secret/aws/1.2.4",
        "owner": "",
        "namespace": "truemark",
        "name": "rds-secret",
        "version": "1.2.4",
        "provider": "aws",
        "provider_logo_url": "/images/providers/aws.png",
        "description": "Creates AWS secrets for AWS RDS instances and clusters",
        "source": "https://github.com/truemark/terraform-aws-rds-secret",
        "tag": "v1.2.4",
        "published_at": "2024-06-14T01:13:18.343457Z",
        "downloads": 4877,
        "verified": false
    },
    {
        "id": "popravak/linuxvm-webserver/azurerm/1.0.18",
        "owner": "",
        "namespace": "popravak",
        "name": "linuxvm-webserver",
        "version": "1.0.18",
        "provider": "azurerm",
        "provider_logo_url": "/images/providers/azure.png?3",
        "description": "Ubuntu w/ Apache and PHP",
        "source": "https://github.com/popravak/terraform-azurerm-linuxvm-webserver",
        "tag": "1.0.18",
        "published_at": "2022-11-06T19:43:57.37388Z",
        "downloads": 1733,
        "verified": false
    },
    {
        "id": "truemark/rds-aurora-postgres-serverless-v2/aws/0.0.5",
        "owner": "",
        "namespace": "truemark",
        "name": "rds-aurora-postgres-serverless-v2",
        "version": "0.0.5",
        "provider": "aws",
        "provider_logo_url": "/images/providers/aws.png",
        "description": "Terraform module used to standup AWS Aurora Serverless V2 PostgreSQL instances",
        "source": "https://github.com/truemark/terraform-aws-rds-aurora-postgres-serverless-v2",
        "tag": "v0.0.5",
        "published_at": "2024-06-14T00:05:02.095611Z",
        "downloads": 1806,
        "verified": false
    },
    {
        "id": "spotinst/ocean-eks-v2/spotinst/3.2.0",
        "owner": "",
        "namespace": "spotinst",
        "name": "ocean-eks-v2",
        "version": "3.2.0",
        "provider": "spotinst",
        "provider_logo_url": "/images/providers/generic.svg?2",
        "description": "clone from terraform-spotinst-ocean-eks",
        "source": "https://github.com/spotinst/terraform-spotinst-ocean-eks-v2",
        "tag": "v3.2.0",
        "published_at": "2022-11-03T10:30:29.532161Z",
        "downloads": 11,
        "verified": false
    },
    {
        "id": "idjemaoune/secrets/aws/1.0.1",
        "owner": "",
        "namespace": "idjemaoune",
        "name": "secrets",
        "version": "1.0.1",
        "provider": "aws",
        "provider_logo_url": "/images/providers/aws.png",
        "description": "",
        "source": "https://github.com/idjemaoune/terraform-aws-secrets",
        "tag": "v1.0.1",
        "published_at": "2022-11-03T11:59:26.768516Z",
        "downloads": 2430,
        "verified": false
    },
    {
        "id": "mergermarket/image-lambda/acuris/0.0.1",
        "owner": "",
        "namespace": "mergermarket",
        "name": "image-lambda",
        "version": "0.0.1",
        "provider": "acuris",
        "provider_logo_url": "/images/providers/generic.svg?2",
        "description": "",
        "source": "https://github.com/mergermarket/terraform-acuris-image-lambda",
        "tag": "0.0.1",
        "published_at": "2022-11-03T15:06:11.446466Z",
        "downloads": 102,
        "verified": false
    },
    {
        "id": "devranaydin/newrelic-cloudformation/aws/1.0.0",
        "owner": "",
        "namespace": "devranaydin",
        "name": "newrelic-cloudformation",
        "version": "1.0.0",
        "provider": "aws",
        "provider_logo_url": "/images/providers/aws.png",
        "description": "Newrelic Integration Aws Account",
        "source": "https://github.com/devranaydin/terraform-aws-newrelic-cloudformation",
        "tag": "v1.0.0",
        "published_at": "2023-11-13T17:56:58.129063Z",
        "downloads": 770,
        "verified": false
    },
    {
        "id": "so1omon563/ecs-fargate-cluster/aws/1.0.2",
        "owner": "",
        "namespace": "so1omon563",
        "name": "ecs-fargate-cluster",
        "version": "1.0.2",
        "provider": "aws",
        "provider_logo_url": "/images/providers/aws.png",
        "description": "Module to create and manage a FARGATE ECS cluster.",
        "source": "https://github.com/so1omon563/terraform-aws-ecs-fargate-cluster",
        "tag": "v1.0.2",
        "published_at": "2023-03-14T19:16:25.470961Z",
        "downloads": 1704,
        "verified": false
    },
    {
        "id": "so1omon563/ecs-task-definition/aws/1.0.0",
        "owner": "",
        "namespace": "so1omon563",
        "name": "ecs-task-definition",
        "version": "1.0.0",
        "provider": "aws",
        "provider_logo_url": "/images/providers/aws.png",
        "description": "Module to create a task definition for use in an ECS service.",
        "source": "https://github.com/so1omon563/terraform-aws-ecs-task-definition",
        "tag": "v1.0.0",
        "published_at": "2022-11-03T20:12:28.084354Z",
        "downloads": 1702,
        "verified": false
    },
    {
        "id": "web-virtua-aws-multi-account-modules/s3/aws/1.0.5",
        "owner": "",
        "namespace": "web-virtua-aws-multi-account-modules",
        "name": "s3",
        "version": "1.0.5",
        "provider": "aws",
        "provider_logo_url": "/images/providers/aws.png",
        "description": "",
        "source": "https://github.com/web-virtua-aws-multi-account-modules/terraform-aws-s3",
        "tag": "v1.0.5",
        "published_at": "2023-10-20T18:19:42.584648Z",
        "downloads": 1828,
        "verified": false
    },
    {
        "id": "caherrera/route53-gsuite-mx/aws/1.0.0",
        "owner": "",
        "namespace": "caherrera",
        "name": "route53-gsuite-mx",
        "version": "1.0.0",
        "provider": "aws",
        "provider_logo_url": "/images/providers/aws.png",
        "description": "",
        "source": "https://github.com/caherrera/terraform-aws-route53-gsuite-mx",
        "tag": "v1.0.0",
        "published_at": "2022-11-04T01:58:47.939292Z",
        "downloads": 1711,
        "verified": false
    },
    {
        "id": "poroping/secure-vnet-nva/azurerm/0.0.1",
        "owner": "",
        "namespace": "poroping",
        "name": "secure-vnet-nva",
        "version": "0.0.1",
        "provider": "azurerm",
        "provider_logo_url": "/images/providers/azure.png?3",
        "description": "",
        "source": "https://github.com/poroping/terraform-azurerm-secure-vnet-nva",
        "tag": "v0.0.1",
        "published_at": "2022-11-04T02:15:40.789188Z",
        "downloads": 0,
        "verified": false
    },
    {
        "id": "littlejo/backup/aws/0.1.0",
        "owner": "",
        "namespace": "littlejo",
        "name": "backup",
        "version": "0.1.0",
        "provider": "aws",
        "provider_logo_url": "/images/providers/aws.png",
        "description": "Deploy aws backup with terraform",
        "source": "https://github.com/littlejo/terraform-aws-backup",
        "tag": "v0.1",
        "published_at": "2022-11-04T09:39:42.9443Z",
        "downloads": 1763,
        "verified": false
    },
    {
        "id": "dasmeta/rabbitmq/aws/1.0.2",
        "owner": "",
        "namespace": "dasmeta",
        "name": "rabbitmq",
        "version": "1.0.2",
        "provider": "aws",
        "provider_logo_url": "/images/providers/aws.png",
        "description": "Terraform modules from DasMeta to manage AWS monitoring resources",
        "source": "https://github.com/dasmeta/terraform-aws-rabbitmq",
        "tag": "v1.0.2",
        "published_at": "2024-03-13T13:40:20.345295Z",
        "downloads": 1819,
        "verified": false
    },
    {
        "id": "littlejo/s3-replication/aws/0.1.0",
        "owner": "",
        "namespace": "littlejo",
        "name": "s3-replication",
        "version": "0.1.0",
        "provider": "aws",
        "provider_logo_url": "/images/providers/aws.png",
        "description": "Deploy AWS S3 with replication",
        "source": "https://github.com/littlejo/terraform-aws-s3-replication",
        "tag": "v0.1",
        "published_at": "2022-11-04T13:26:42.151253Z",
        "downloads": 0,
        "verified": false
    },
    {
        "id": "data-platform-hq/data-factory-linked-services/azurerm/1.3.1",
        "owner": "",
        "namespace": "data-platform-hq",
        "name": "data-factory-linked-services",
        "version": "1.3.1",
        "provider": "azurerm",
        "provider_logo_url": "/images/providers/azure.png?3",
        "description": "Terraform module for managing Azure Data Factory linked services",
        "source": "https://github.com/data-platform-hq/terraform-azurerm-data-factory-linked-services",
        "tag": "v1.3.1",
        "published_at": "2024-05-25T20:17:39.217988Z",
        "downloads": 6913,
        "verified": false
    },
    {
        "id": "bloodyrw/apache-example/aws/1.0.0",
        "owner": "",
        "namespace": "bloodyrw",
        "name": "apache-example",
        "version": "1.0.0",
        "provider": "aws",
        "provider_logo_url": "/images/providers/aws.png",
        "description": "",
        "source": "https://github.com/rafalwitalski/terraform-aws-apache-example",
        "tag": "1.0.0",
        "published_at": "2022-11-04T14:40:22.711224Z",
        "downloads": 0,
        "verified": false
    },
    {
        "id": "cktf/application/gitlab/1.3.1",
        "owner": "",
        "namespace": "cktf",
        "name": "application",
        "version": "1.3.1",
        "provider": "gitlab",
        "provider_logo_url": "/images/providers/generic.svg?2",
        "description": "Terraform Gitlab Application Module",
        "source": "https://github.com/cktf/terraform-gitlab-application",
        "tag": "1.3.1",
        "published_at": "2022-11-10T09:32:38.291197Z",
        "downloads": 18,
        "verified": false
    },
    {
        "id": "jakoberpf/peering-local/oracle/0.1.4",
        "owner": "",
        "namespace": "jakoberpf",
        "name": "peering-local",
        "version": "0.1.4",
        "provider": "oracle",
        "provider_logo_url": "/images/providers/oracle.png",
        "description": "Terreform module for integrated service deployment",
        "source": "https://github.com/jakoberpf/terraform-oracle-peering-local",
        "tag": "0.1.4",
        "published_at": "2023-10-25T05:52:28.387124Z",
        "downloads": 162,
        "verified": false
    },
    {
        "id": "rafalwitalski/apache-example/aws/1.0.0",
        "owner": "",
        "namespace": "rafalwitalski",
        "name": "apache-example",
        "version": "1.0.0",
        "provider": "aws",
        "provider_logo_url": "/images/providers/aws.png",
        "description": "",
        "source": "https://github.com/rafalwitalski/terraform-aws-apache-example",
        "tag": "1.0.0",
        "published_at": "2022-11-04T18:22:53.468375Z",
        "downloads": 1701,
        "verified": false
    },
    {
        "id": "r-teller/restricted-subnetworks/google/1.0.1",
        "owner": "",
        "namespace": "r-teller",
        "name": "restricted-subnetworks",
        "version": "1.0.1",
        "provider": "google",
        "provider_logo_url": "/images/providers/google-cloud.svg",
        "description": "",
        "source": "https://github.com/r-teller/terraform-google-restricted-subnetworks",
        "tag": "1.0.1",
        "published_at": "2022-11-04T21:24:46.288279Z",
        "downloads": 1638,
        "verified": false
    },
    {
        "id": "SPHTech-Platform/kube-prometheus-stack/helm/0.1.2",
        "owner": "",
        "namespace": "SPHTech-Platform",
        "name": "kube-prometheus-stack",
        "version": "0.1.2",
        "provider": "helm",
        "provider_logo_url": "/images/providers/helm.svg?3",
        "description": "Installs the kube-prometheus stack, a collection of Kubernetes manifests, Grafana dashboards, and Prometheus rules combined with documentation and scripts to provide easy to operate end-to-end Kubernetes cluster monitoring with Prometheus using the Prometheus Operator.",
        "source": "https://github.com/SPHTech-Platform/terraform-helm-kube-prometheus-stack",
        "tag": "v0.1.2",
        "published_at": "2023-02-10T03:37:45.292292Z",
        "downloads": 8239,
        "verified": false
    },
    {
        "id": "mateothegreat/metrics-server/kubernetes/0.0.3",
        "owner": "",
        "namespace": "mateothegreat",
        "name": "metrics-server",
        "version": "0.0.3",
        "provider": "kubernetes",
        "provider_logo_url": "/images/providers/kubernetes.svg",
        "description": "Kubernetes metrcis-server via Terraform",
        "source": "https://github.com/mateothegreat/terraform-kubernetes-metrics-server",
        "tag": "0.0.3",
        "published_at": "2022-11-06T17:21:03.800776Z",
        "downloads": 1940,
        "verified": false
    },
    {
        "id": "truemark/rds-mysql/aws/2.0.2",
        "owner": "",
        "namespace": "truemark",
        "name": "rds-mysql",
        "version": "2.0.2",
        "provider": "aws",
        "provider_logo_url": "/images/providers/aws.png",
        "description": "Terraform module for standing up standard MySQL RDS instances with built-in alerts etc..",
        "source": "https://github.com/truemark/terraform-aws-rds-mysql",
        "tag": "v2.0.2",
        "published_at": "2024-06-14T00:56:12.739847Z",
        "downloads": 1849,
        "verified": false
    },
    {
        "id": "libre-devops/availability-set-proximity-group/azurerm/1.0.0",
        "owner": "",
        "namespace": "libre-devops",
        "name": "availability-set-proximity-group",
        "version": "1.0.0",
        "provider": "azurerm",
        "provider_logo_url": "/images/providers/azure.png?3",
        "description": "A module to create a availability set, proximity placement group or both",
        "source": "https://github.com/libre-devops/terraform-azurerm-availability-set-proximity-group",
        "tag": "1.0.0",
        "published_at": "2022-11-06T22:55:06.421835Z",
        "downloads": 1688,
        "verified": false
    },
    {
        "id": "SPHTech-Platform/release/helm/0.1.4",
        "owner": "",
        "namespace": "SPHTech-Platform",
        "name": "release",
        "version": "0.1.4",
        "provider": "helm",
        "provider_logo_url": "/images/providers/helm.svg?3",
        "description": "Terraform module to deploy a generic Helm Chart",
        "source": "https://github.com/SPHTech-Platform/terraform-helm-release",
        "tag": "v0.1.4",
        "published_at": "2023-07-06T07:45:33.310813Z",
        "downloads": 108511,
        "verified": false
    },
    {
        "id": "poroping/hub-vxlan-interconnect/fortios/0.0.1",
        "owner": "",
        "namespace": "poroping",
        "name": "hub-vxlan-interconnect",
        "version": "0.0.1",
        "provider": "fortios",
        "provider_logo_url": "/images/providers/generic.svg?2",
        "description": "",
        "source": "https://github.com/poroping/terraform-fortios-hub-vxlan-interconnect",
        "tag": "v0.0.1",
        "published_at": "2022-11-07T04:50:03.537703Z",
        "downloads": 0,
        "verified": false
    },
    {
        "id": "web-virtua-aws-multi-account-modules/ecr/aws/1.0.2",
        "owner": "",
        "namespace": "web-virtua-aws-multi-account-modules",
        "name": "ecr",
        "version": "1.0.2",
        "provider": "aws",
        "provider_logo_url": "/images/providers/aws.png",
        "description": "",
        "source": "https://github.com/web-virtua-aws-multi-account-modules/terraform-aws-ecr",
        "tag": "v1.0.2",
        "published_at": "2022-11-07T17:20:01.195084Z",
        "downloads": 1740,
        "verified": false
    },
    {
        "id": "TaitoUnited/email/sendgrid/1.1.0",
        "owner": "",
        "namespace": "TaitoUnited",
        "name": "email",
        "version": "1.1.0",
        "provider": "sendgrid",
        "provider_logo_url": "/images/providers/generic.svg?2",
        "description": "",
        "source": "https://github.com/TaitoUnited/terraform-sendgrid-email",
        "tag": "v1.1.0",
        "published_at": "2022-11-07T20:46:21.238879Z",
        "downloads": 15,
        "verified": false
    },
    {
        "id": "data-platform-hq/eventgrid-topic/azurerm/1.1.0",
        "owner": "",
        "namespace": "data-platform-hq",
        "name": "eventgrid-topic",
        "version": "1.1.0",
        "provider": "azurerm",
        "provider_logo_url": "/images/providers/azure.png?3",
        "description": "Terraform module for managing Azure Event Grid Topic",
        "source": "https://github.com/data-platform-hq/terraform-azurerm-eventgrid-topic",
        "tag": "v1.1.0",
        "published_at": "2023-01-27T17:54:31.961438Z",
        "downloads": 5763,
        "verified": false
    },
    {
        "id": "data-platform-hq/logic-app-workflow/azurerm/1.2.1",
        "owner": "",
        "namespace": "data-platform-hq",
        "name": "logic-app-workflow",
        "version": "1.2.1",
        "provider": "azurerm",
        "provider_logo_url": "/images/providers/azure.png?3",
        "description": "",
        "source": "https://github.com/data-platform-hq/terraform-azurerm-logic-app-workflow",
        "tag": "v1.2.1",
        "published_at": "2023-02-01T17:41:13.792166Z",
        "downloads": 9845,
        "verified": false
    },
    {
        "id": "jamerply/s3backend/aws/0.2.0",
        "owner": "",
        "namespace": "jamerply",
        "name": "s3backend",
        "version": "0.2.0",
        "provider": "aws",
        "provider_logo_url": "/images/providers/aws.png",
        "description": "Deploys and s3 remote backend for Terraform",
        "source": "https://github.com/jamerply/terraform-aws-s3backend",
        "tag": "v0.2.0",
        "published_at": "2022-11-07T18:45:59.751158Z",
        "downloads": 1675,
        "verified": false
    },
    {
        "id": "liatrio/github-runner/azure/0.1.3",
        "owner": "",
        "namespace": "liatrio",
        "name": "github-runner",
        "version": "0.1.3",
        "provider": "azure",
        "provider_logo_url": "/images/providers/azure.png?3",
        "description": "Terraform module for scalable GitHub action runners on Azure",
        "source": "https://github.com/liatrio/terraform-azure-github-runner",
        "tag": "0.1.3",
        "published_at": "2024-01-25T15:52:43.516545Z",
        "downloads": 1375,
        "verified": false
    },
    {
        "id": "SPHTech-Platform/opensearch/aws/2.4.6",
        "owner": "",
        "namespace": "SPHTech-Platform",
        "name": "opensearch",
        "version": "2.4.6",
        "provider": "aws",
        "provider_logo_url": "/images/providers/aws.png",
        "description": "Terraform module to create aws opensearch (elasticsearch)",
        "source": "https://github.com/SPHTech-Platform/terraform-aws-opensearch",
        "tag": "v2.4.6",
        "published_at": "2024-07-26T02:27:53.029967Z",
        "downloads": 72142,
        "verified": false
    },
    {
        "id": "Nuagic/ecs-slack-alerts/aws/1.1.0",
        "owner": "",
        "namespace": "Nuagic",
        "name": "ecs-slack-alerts",
        "version": "1.1.0",
        "provider": "aws",
        "provider_logo_url": "/images/providers/aws.png",
        "description": "",
        "source": "https://github.com/Nuagic/terraform-aws-ecs-slack-alerts",
        "tag": "v1.1.0",
        "published_at": "2023-10-04T07:46:02.353419Z",
        "downloads": 4852,
        "verified": false
    },
    {
        "id": "terraform-tencentcloud-modules/cfs/tencentcloud/0.2.0",
        "owner": "",
        "namespace": "terraform-tencentcloud-modules",
        "name": "cfs",
        "version": "0.2.0",
        "provider": "tencentcloud",
        "provider_logo_url": "/images/providers/generic.svg?2",
        "description": "TencentCloud CFS Storage Module for Terraform",
        "source": "https://github.com/terraform-tencentcloud-modules/terraform-tencentcloud-cfs",
        "tag": "v0.2.0",
        "published_at": "2023-11-06T07:46:58.746416Z",
        "downloads": 4,
        "verified": false
    },
    {
        "id": "terraform-tencentcloud-modules/cos/tencentcloud/0.4.0",
        "owner": "",
        "namespace": "terraform-tencentcloud-modules",
        "name": "cos",
        "version": "0.4.0",
        "provider": "tencentcloud",
        "provider_logo_url": "/images/providers/generic.svg?2",
        "description": "TencentCloud COS Module for Terraform",
        "source": "https://github.com/terraform-tencentcloud-modules/terraform-tencentcloud-cos",
        "tag": "v0.4.0",
        "published_at": "2024-04-22T12:35:04.984617Z",
        "downloads": 164,
        "verified": false
    },
    {
        "id": "terraform-tencentcloud-modules/eip/tencentcloud/0.1.0",
        "owner": "",
        "namespace": "terraform-tencentcloud-modules",
        "name": "eip",
        "version": "0.1.0",
        "provider": "tencentcloud",
        "provider_logo_url": "/images/providers/generic.svg?2",
        "description": "TencentCloud EIP Module for Terraform",
        "source": "https://github.com/terraform-tencentcloud-modules/terraform-tencentcloud-eip",
        "tag": "v0.1.0",
        "published_at": "2022-11-08T13:44:19.38915Z",
        "downloads": 9,
        "verified": false
    },
    {
        "id": "terraform-tencentcloud-modules/cvm/tencentcloud/1.0.0",
        "owner": "",
        "namespace": "terraform-tencentcloud-modules",
        "name": "cvm",
        "version": "1.0.0",
        "provider": "tencentcloud",
        "provider_logo_url": "/images/providers/generic.svg?2",
        "description": "TencentCloud CVM Storage Module for Terraform",
        "source": "https://github.com/terraform-tencentcloud-modules/terraform-tencentcloud-cvm",
        "tag": "v1.0.0",
        "published_at": "2023-03-27T06:43:37.230809Z",
        "downloads": 639,
        "verified": false
    },
    {
        "id": "terraform-tencentcloud-modules/tke-nodepool/tencentcloud/0.1.0",
        "owner": "",
        "namespace": "terraform-tencentcloud-modules",
        "name": "tke-nodepool",
        "version": "0.1.0",
        "provider": "tencentcloud",
        "provider_logo_url": "/images/providers/generic.svg?2",
        "description": "TencentCloud TKE & Node Pool for Terraform",
        "source": "https://github.com/terraform-tencentcloud-modules/terraform-tencentcloud-tke-nodepool",
        "tag": "v0.1.0",
        "published_at": "2022-11-08T13:46:18.768319Z",
        "downloads": 5,
        "verified": false
    },
    {
        "id": "terraform-tencentcloud-modules/tcr/tencentcloud/0.2.0",
        "owner": "",
        "namespace": "terraform-tencentcloud-modules",
        "name": "tcr",
        "version": "0.2.0",
        "provider": "tencentcloud",
        "provider_logo_url": "/images/providers/generic.svg?2",
        "description": "TencentCloud TCR for Terraform",
        "source": "https://github.com/terraform-tencentcloud-modules/terraform-tencentcloud-tcr",
        "tag": "v0.2.0",
        "published_at": "2023-01-09T07:30:29.67044Z",
        "downloads": 719,
        "verified": false
    },
    {
        "id": "terraform-tencentcloud-modules/ssh/tencentcloud/0.1.0",
        "owner": "",
        "namespace": "terraform-tencentcloud-modules",
        "name": "ssh",
        "version": "0.1.0",
        "provider": "tencentcloud",
        "provider_logo_url": "/images/providers/generic.svg?2",
        "description": "TencentCloud SSH for Terraform",
        "source": "https://github.com/terraform-tencentcloud-modules/terraform-tencentcloud-ssh",
        "tag": "v0.1.0",
        "published_at": "2022-11-08T13:46:25.336065Z",
        "downloads": 11,
        "verified": false
    },
    {
        "id": "terraform-tencentcloud-modules/postgresql/tencentcloud/0.1.0",
        "owner": "",
        "namespace": "terraform-tencentcloud-modules",
        "name": "postgresql",
        "version": "0.1.0",
        "provider": "tencentcloud",
        "provider_logo_url": "/images/providers/generic.svg?2",
        "description": "TencentCloud PostgreSQL for Terraform",
        "source": "https://github.com/terraform-tencentcloud-modules/terraform-tencentcloud-postgresql",
        "tag": "v0.1.0",
        "published_at": "2022-11-08T13:46:26.818922Z",
        "downloads": 3,
        "verified": false
    },
    {
        "id": "terraform-tencentcloud-modules/redis/tencentcloud/1.0.0",
        "owner": "",
        "namespace": "terraform-tencentcloud-modules",
        "name": "redis",
        "version": "1.0.0",
        "provider": "tencentcloud",
        "provider_logo_url": "/images/providers/generic.svg?2",
        "description": "TencentCloud Redis for Terraform",
        "source": "https://github.com/terraform-tencentcloud-modules/terraform-tencentcloud-redis",
        "tag": "v1.0.0",
        "published_at": "2023-03-27T06:18:59.415059Z",
        "downloads": 74,
        "verified": false
    },
    {
        "id": "terraform-tencentcloud-modules/nat/tencentcloud/0.1.0",
        "owner": "",
        "namespace": "terraform-tencentcloud-modules",
        "name": "nat",
        "version": "0.1.0",
        "provider": "tencentcloud",
        "provider_logo_url": "/images/providers/generic.svg?2",
        "description": "TencentCloud NAT Gateway for Terraform",
        "source": "https://github.com/terraform-tencentcloud-modules/terraform-tencentcloud-nat",
        "tag": "v0.1.0",
        "published_at": "2022-11-08T13:46:33.240187Z",
        "downloads": 3,
        "verified": false
    },
    {
        "id": "tf-cloud-modules/vpc/sbercloud/1.0.1",
        "owner": "",
        "namespace": "tf-cloud-modules",
        "name": "vpc",
        "version": "1.0.1",
        "provider": "sbercloud",
        "provider_logo_url": "/images/providers/generic.svg?2",
        "description": "Sbercloud VPC Terraform module",
        "source": "https://github.com/tf-cloud-modules/terraform-sbercloud-vpc",
        "tag": "1.0.1",
        "published_at": "2023-05-30T07:07:32.77044Z",
        "downloads": 8,
        "verified": false
    },
    {
        "id": "web-virtua-aws-multi-account-modules/sqs/aws/1.0.0",
        "owner": "",
        "namespace": "web-virtua-aws-multi-account-modules",
        "name": "sqs",
        "version": "1.0.0",
        "provider": "aws",
        "provider_logo_url": "/images/providers/aws.png",
        "description": "",
        "source": "https://github.com/web-virtua-aws-multi-account-modules/terraform-aws-sqs",
        "tag": "v1.0.0",
        "published_at": "2022-11-08T14:54:22.424333Z",
        "downloads": 1693,
        "verified": false
    },
    {
        "id": "nuvibit/core-parameters/aws/1.1.1",
        "owner": "",
        "namespace": "nuvibit",
        "name": "core-parameters",
        "version": "1.1.1",
        "provider": "aws",
        "provider_logo_url": "/images/providers/aws.png",
        "description": "Terraform module to store and read a terraform HCL map via AWS SSM Parameter Store.",
        "source": "https://github.com/nuvibit/terraform-aws-core-parameters",
        "tag": "1.1.1",
        "published_at": "2023-03-08T13:43:45.374867Z",
        "downloads": 2672,
        "verified": false
    },
    {
        "id": "boeboe/istio/helm/0.0.2",
        "owner": "",
        "namespace": "boeboe",
        "name": "istio",
        "version": "0.0.2",
        "provider": "helm",
        "provider_logo_url": "/images/providers/helm.svg?3",
        "description": "Terraform module for Istio deployment on Kubernetes using Helm",
        "source": "https://github.com/boeboe/terraform-helm-istio",
        "tag": "0.0.2",
        "published_at": "2022-11-08T21:21:13.019298Z",
        "downloads": 52,
        "verified": false
    },
    {
        "id": "kalenarndt/consul-k8s-integration/vault/0.0.5",
        "owner": "",
        "namespace": "kalenarndt",
        "name": "consul-k8s-integration",
        "version": "0.0.5",
        "provider": "vault",
        "provider_logo_url": "/images/providers/vault.svg?3",
        "description": "Module that configures all of the secrets engines, secrets, and certificates for Consul to use",
        "source": "https://github.com/kalenarndt/terraform-vault-consul-k8s-integration",
        "tag": "0.0.5",
        "published_at": "2023-02-17T16:31:45.39206Z",
        "downloads": 0,
        "verified": false
    },
    {
        "id": "kalenarndt/vault-external-helm-setup/kubernetes/0.0.1",
        "owner": "",
        "namespace": "kalenarndt",
        "name": "vault-external-helm-setup",
        "version": "0.0.1",
        "provider": "kubernetes",
        "provider_logo_url": "/images/providers/kubernetes.svg",
        "description": "Terraform module to template a helm file for the use of an external Vault instance",
        "source": "https://github.com/kalenarndt/terraform-kubernetes-vault-external-helm-setup",
        "tag": "0.0.1",
        "published_at": "2022-11-08T17:42:32.095413Z",
        "downloads": 1619,
        "verified": false
    },
    {
        "id": "lacework/alerts-to-s3/aws/0.4.1",
        "owner": "",
        "namespace": "lacework",
        "name": "alerts-to-s3",
        "version": "0.4.1",
        "provider": "aws",
        "provider_logo_url": "/images/providers/aws.png",
        "description": "Terraform Lacework Alerts to AWS-S3",
        "source": "https://github.com/lacework/terraform-aws-alerts-to-s3",
        "tag": "v0.4.1",
        "published_at": "2023-06-07T10:43:26.66515Z",
        "downloads": 1380,
        "verified": false
    },
    {
        "id": "kalenarndt/kubernetes-auth/vault/0.0.2",
        "owner": "",
        "namespace": "kalenarndt",
        "name": "kubernetes-auth",
        "version": "0.0.2",
        "provider": "vault",
        "provider_logo_url": "/images/providers/vault.svg?3",
        "description": "Terraform Module that creates a basic Kubernetes auth method",
        "source": "https://github.com/kalenarndt/terraform-vault-kubernetes-auth",
        "tag": "0.0.2",
        "published_at": "2022-11-08T18:06:14.612342Z",
        "downloads": 7,
        "verified": false
    },
    {
        "id": "AkgunD/docker-instance/aws/0.0.1",
        "owner": "",
        "namespace": "AkgunD",
        "name": "docker-instance",
        "version": "0.0.1",
        "provider": "aws",
        "provider_logo_url": "/images/providers/aws.png",
        "description": "",
        "source": "https://github.com/AkgunD/terraform-aws-docker-instance",
        "tag": "v0.0.1",
        "published_at": "2022-11-08T18:33:38.040472Z",
        "downloads": 1678,
        "verified": false
    },
    {
        "id": "allybazz/docker-instance/aws/0.0.1",
        "owner": "",
        "namespace": "allybazz",
        "name": "docker-instance",
        "version": "0.0.1",
        "provider": "aws",
        "provider_logo_url": "/images/providers/aws.png",
        "description": "",
        "source": "https://github.com/allybazz/terraform-aws-docker-instance",
        "tag": "v0.0.1",
        "published_at": "2022-11-08T19:25:00.888312Z",
        "downloads": 0,
        "verified": false
    },
    {
        "id": "osmnnunal/docker-instance-try/aws/0.0.1",
        "owner": "",
        "namespace": "osmnnunal",
        "name": "docker-instance-try",
        "version": "0.0.1",
        "provider": "aws",
        "provider_logo_url": "/images/providers/aws.png",
        "description": "",
        "source": "https://github.com/osmnnunal/terraform-aws-docker-instance-try",
        "tag": "v0.0.1",
        "published_at": "2022-11-08T19:26:01.393994Z",
        "downloads": 0,
        "verified": false
    },
    {
        "id": "ozulfikar/docker-instance/aws/0.0.1",
        "owner": "",
        "namespace": "ozulfikar",
        "name": "docker-instance",
        "version": "0.0.1",
        "provider": "aws",
        "provider_logo_url": "/images/providers/aws.png",
        "description": "",
        "source": "https://github.com/ozulfikar/terraform-aws-docker-instance",
        "tag": "v0.0.1",
        "published_at": "2022-11-08T19:30:20.747431Z",
        "downloads": 1678,
        "verified": false
    },
    {
        "id": "Mustafacan76/docker-instance/aws/0.0.1",
        "owner": "",
        "namespace": "Mustafacan76",
        "name": "docker-instance",
        "version": "0.0.1",
        "provider": "aws",
        "provider_logo_url": "/images/providers/aws.png",
        "description": "",
        "source": "https://github.com/Mustafacan76/terraform-aws-docker-instance",
        "tag": "v0.0.1",
        "published_at": "2022-11-08T19:30:42.430926Z",
        "downloads": 1679,
        "verified": false
    },
    {
        "id": "eakkaya64/docker-instance/aws/0.0.1",
        "owner": "",
        "namespace": "eakkaya64",
        "name": "docker-instance",
        "version": "0.0.1",
        "provider": "aws",
        "provider_logo_url": "/images/providers/aws.png",
        "description": "",
        "source": "https://github.com/eakkaya64/terraform-aws-docker-instance",
        "tag": "v0.0.1",
        "published_at": "2022-11-08T19:30:48.426239Z",
        "downloads": 1677,
        "verified": false
    }
]
